Workbook

Sheet Base Cruz
A1: Cliente | B1: Razão Social | C1: AG | D1: Caixas Comodatadas | E1: Vol. Real Hl Trimestral | F1: Vol. Real Cx Trimestral | G1: Giro Trimestral | H1: Vol. Real Hl Mensal | I1: Vol. Real Cx Mensal | J1: Giro | K1: Tend. Giro | L1: Meta Unit. | M1: Item Comodato | N1: tipo | O1: Quantidade | P1: Valor Uni. | Q1: Valor Tot. | R1: Tipo Giro Trimestral | S1: Tipo Giro Mensal | T1: Nome Fantasia | U1: Setor | V1: GV | W1: Tipo de Vasilhame | X1: Comprou | Y1: Falta Comprar | Z1: Meta | AA1: Tendência | AF1: INICIO DO MÊS | AG1: HOJE | AH1: INICIO DO MÊS - HOJE
A2: 197 | B2: ACARAU CONVENIENCIA | C2: Cerveja 1/2 | D2: 6 | E2: 0.41 | F2: 6 | G2: 0.22 | H2: 0 | I2: 0 | J2: 0 | K2: 0 | L2: 1.5 | M2: 296156 | N2: GARRAFEIRA PLAST,23 GFA 300ML,AZUL | O2: 6 | P2: 29.77 | Q2: 178.62 | R2: Não OK | S2: Zero | T2: =VLOOKUP(Tabela2[[#This Row],[Cliente]],Setor!$C$2:$F$1606,4,0) -> ZE - ARMAZEM EXPRESS | U2: =VLOOKUP(Tabela2[[#This Row],[Cliente]],Setor!$C:$AU,45,0) -> 501 | V2: =_xlfn.XLOOKUP(Tabela2[[#This Row],[Setor]],AD:AD,AE:AE) -> Fredson | W2: =IF(Tabela2[[#This Row],[Meta Unit.]]=2,"SEISCENTOS","LITRINHO") -> LITRINHO | X2: =Tabela2[[#This Row],[Vol. Real Cx Mensal]] -> 0 | Y2: =(Tabela2[[#This Row],[Caixas Comodatadas]]*Tabela2[[#This Row],[Meta Unit.]])-Tabela2[[#This Row],[Comprou]] -> 9 | Z2: =IF(Tabela2[[#This Row],[Tipo de Vasilhame]] = "LITRINHO",1.5*Tabela2[[#This Row],[Caixas Comodatadas]],Tabela2[[#This Row],[Caixas Comodatadas]]*2) -> 9 | AA2: =IFERROR(IF(OR(FIND("OK", Tabela2[[#This Row],[Tipo Giro Mensal]]) > 0), IF(Tabela2[[#This Row],[Comprou]]/$AH$2*30 > Tabela2[[#This Row],[Meta]], "BATE", "ABAIXO"), "-"),"-") -> - | AF2: 46082 | AG2: =TODAY() -> 46111 | AH2: =AG2-AF2 -> 29
A3: 221 | B3: JOSE ZILMAR ARAUJO | C3: Cerveja 1/2 | D3: 5 | E3: 6.55 | F3: 95 | G3: 4.22 | H3: 1.17 | I3: 17 | J3: 2.27 | K3: 21.25 | L3: 1.5 | M3: 296156 | N3: GARRAFEIRA PLAST,23 GFA 300ML,AZUL | O3: 5 | P3: 29.77 | Q3: 148.85 | R3: OK | S3: OK | T3: =VLOOKUP(Tabela2[[#This Row],[Cliente]],Setor!$C$2:$F$1606,4,0) -> RANCHO DA ROCA | U3: =VLOOKUP(Tabela2[[#This Row],[Cliente]],Setor!$C:$AU,45,0) -> 102 | V3: =_xlfn.XLOOKUP(Tabela2[[#This Row],[Setor]],AD:AD,AE:AE) -> Fredson | W3: =IF(Tabela2[[#This Row],[Meta Unit.]]=2,"SEISCENTOS","LITRINHO") -> LITRINHO | X3: =Tabela2[[#This Row],[Vol. Real Cx Mensal]] -> 17 | Y3: =(Tabela2[[#This Row],[Caixas Comodatadas]]*Tabela2[[#This Row],[Meta Unit.]])-Tabela2[[#This Row],[Comprou]] -> -9.5 | Z3: =IF(Tabela2[[#This Row],[Tipo de Vasilhame]] = "LITRINHO",1.5*Tabela2[[#This Row],[Caixas Comodatadas]],Tabela2[[#This Row],[Caixas Comodatadas]]*2) -> 7.5 | AA3: =IFERROR(IF(OR(FIND("OK", Tabela2[[#This Row],[Tipo Giro Mensal]]) > 0), IF(Tabela2[[#This Row],[Comprou]]/$AH$2*30 > Tabela2[[#This Row],[Meta]], "BATE", "ABAIXO"), "-"),"-") -> BATE | AD3: SETORES | AE3: GV
A4: 271 | B4: JACINTA GUILHERME DE SOUSA SANTOS | C4: Cerveja 1/2 | D4: 2 | E4: 0.82 | F4: 12 | G4: 1.33 | H4: 0.27 | I4: 4 | J4: 1.33 | K4: 5 | L4: 1.5 | M4: 296156 | N4: GARRAFEIRA PLAST,23 GFA 300ML,AZUL | O4: 2 | P4: 29.77 | Q4: 59.54 | R4: OK | S4: OK | T4: =VLOOKUP(Tabela2[[#This Row],[Cliente]],Setor!$C$2:$F$1606,4,0) -> BAR DA JACINTA CORR | U4: =VLOOKUP(Tabela2[[#This Row],[Cliente]],Setor!$C:$AU,45,0) -> 104 | V4: =_xlfn.XLOOKUP(Tabela2[[#This Row],[Setor]],AD:AD,AE:AE) -> Fredson | W4: =IF(Tabela2[[#This Row],[Meta Unit.]]=2,"SEISCENTOS","LITRINHO") -> LITRINHO | X4: =Tabela2[[#This Row],[Vol. Real Cx Mensal]] -> 4 | Y4: =(Tabela2[[#This Row],[Caixas Comodatadas]]*Tabela2[[#This Row],[Meta Unit.]])-Tabela2[[#This Row],[Comprou]] -> -1 | Z4: =IF(Tabela2[[#This Row],[Tipo de Vasilhame]] = "LITRINHO",1.5*Tabela2[[#This Row],[Caixas Comodatadas]],Tabela2[[#This Row],[Caixas Comodatadas]]*2) -> 3 | AA4: =IFERROR(IF(OR(FIND("OK", Tabela2[[#This Row],[Tipo Giro Mensal]]) > 0), IF(Tabela2[[#This Row],[Comprou]]/$AH$2*30 > Tabela2[[#This Row],[Meta]], "BATE", "ABAIXO"), "-"),"-") -> BATE | AD4: 100 | AE4: Jaissa
A5: 320 | B5: FRANCISCO RICARDO ARAUJO | C5: Cerveja 1/2 | D5: 10 | E5: 11.52 | F5: 167 | G5: 3.71 | H5: 0 | I5: 0 | J5: 0 | K5: 0 | L5: 1.5 | M5: 296156 | N5: GARRAFEIRA PLAST,23 GFA 300ML,AZUL | O5: 10 | P5: 29.77 | Q5: 297.7 | R5: OK | S5: Zero Total | T5: =VLOOKUP(Tabela2[[#This Row],[Cliente]],Setor!$C$2:$F$1606,4,0) -> MERC RICARDO TIMBIR | U5: =VLOOKUP(Tabela2[[#This Row],[Cliente]],Setor!$C:$AU,45,0) -> 105 | V5: =_xlfn.XLOOKUP(Tabela2[[#This Row],[Setor]],AD:AD,AE:AE) -> Jaissa | W5: =IF(Tabela2[[#This Row],[Meta Unit.]]=2,"SEISCENTOS","LITRINHO") -> LITRINHO | X5: =Tabela2[[#This Row],[Vol. Real Cx Mensal]] -> 0 | Y5: =(Tabela2[[#This Row],[Caixas Comodatadas]]*Tabela2[[#This Row],[Meta Unit.]])-Tabela2[[#This Row],[Comprou]] -> 15 | Z5: =IF(Tabela2[[#This Row],[Tipo de Vasilhame]] = "LITRINHO",1.5*Tabela2[[#This Row],[Caixas Comodatadas]],Tabela2[[#This Row],[Caixas Comodatadas]]*2) -> 15 | AA5: =IFERROR(IF(OR(FIND("OK", Tabela2[[#This Row],[Tipo Giro Mensal]]) > 0), IF(Tabela2[[#This Row],[Comprou]]/$AH$2*30 > Tabela2[[#This Row],[Meta]], "BATE", "ABAIXO"), "-"),"-") -> - | AD5: 103 | AE5: Jaissa
A6: 345 | B6: MARIA ELIANE SILVEIRA | C6: Cerveja 1/2 | D6: 4 | E6: 5.38 | F6: 78 | G6: 4.33 | H6: 0.69 | I6: 10 | J6: 1.67 | K6: 12.5 | L6: 1.5 | M6: 296156 | N6: GARRAFEIRA PLAST,23 GFA 300ML,AZUL | O6: 4 | P6: 29.77 | Q6: 119.08 | R6: OK | S6: OK | T6: =VLOOKUP(Tabela2[[#This Row],[Cliente]],Setor!$C$2:$F$1606,4,0) -> BAR DO COXINHA CRUZ | U6: =VLOOKUP(Tabela2[[#This Row],[Cliente]],Setor!$C:$AU,45,0) -> 105 | V6: =_xlfn.XLOOKUP(Tabela2[[#This Row],[Setor]],AD:AD,AE:AE) -> Jaissa | W6: =IF(Tabela2[[#This Row],[Meta Unit.]]=2,"SEISCENTOS","LITRINHO") -> LITRINHO | X6: =Tabela2[[#This Row],[Vol. Real Cx Mensal]] -> 10 | Y6: =(Tabela2[[#This Row],[Caixas Comodatadas]]*Tabela2[[#This Row],[Meta Unit.]])-Tabela2[[#This Row],[Comprou]] -> -4 | Z6: =IF(Tabela2[[#This Row],[Tipo de Vasilhame]] = "LITRINHO",1.5*Tabela2[[#This Row],[Caixas Comodatadas]],Tabela2[[#This Row],[Caixas Comodatadas]]*2) -> 6 | AA6: =IFERROR(IF(OR(FIND("OK", Tabela2[[#This Row],[Tipo Giro Mensal]]) > 0), IF(Tabela2[[#This Row],[Comprou]]/$AH$2*30 > Tabela2[[#This Row],[Meta]], "BATE", "ABAIXO"), "-"),"-") -> BATE | AD6: 105 | AE6: Jaissa
A7: 388 | B7: FRANCISCO LEANDRO CRUZ ME | C7: Cerveja 1/1 | D7: 6 | E7: 0 | F7: 0 | G7: 0 | H7: 0.57 | I7: 4 | J7: 0.33 | K7: 5 | L7: 2 | M7: 103330 | N7: GARRAFEIRA PLAST,24 GFA 600ML,ANTARCTICA, | O7: 6 | P7: 43.86 | Q7: 263.16 | R7: Zero | S7: Não OK | T7: =VLOOKUP(Tabela2[[#This Row],[Cliente]],Setor!$C$2:$F$1606,4,0) -> SUPERMERCADO SKINAO | U7: =VLOOKUP(Tabela2[[#This Row],[Cliente]],Setor!$C:$AU,45,0) -> 501 | V7: =_xlfn.XLOOKUP(Tabela2[[#This Row],[Setor]],AD:AD,AE:AE) -> Fredson | W7: =IF(Tabela2[[#This Row],[Meta Unit.]]=2,"SEISCENTOS","LITRINHO") -> SEISCENTOS | X7: =Tabela2[[#This Row],[Vol. Real Cx Mensal]] -> 4 | Y7: =(Tabela2[[#This Row],[Caixas Comodatadas]]*Tabela2[[#This Row],[Meta Unit.]])-Tabela2[[#This Row],[Comprou]] -> 8 | Z7: =IF(Tabela2[[#This Row],[Tipo de Vasilhame]] = "LITRINHO",1.5*Tabela2[[#This Row],[Caixas Comodatadas]],Tabela2[[#This Row],[Caixas Comodatadas]]*2) -> 12 | AA7: =IFERROR(IF(OR(FIND("OK", Tabela2[[#This Row],[Tipo Giro Mensal]]) > 0), IF(Tabela2[[#This Row],[Comprou]]/$AH$2*30 > Tabela2[[#This Row],[Meta]], "BATE", "ABAIXO"), "-"),"-") -> ABAIXO | AD7: 106 | AE7: Jaissa
A8: 388 | B8: FRANCISCO LEANDRO CRUZ ME | C8: Cerveja 1/2 | D8: 50 | E8: 8.83 | F8: 128 | G8: 0.57 | H8: 1.03 | I8: 15 | J8: 0.2 | K8: 18.75 | L8: 1.5 | M8: 296156 | N8: GARRAFEIRA PLAST,23 GFA 300ML,AZUL | O8: 50 | P8: 29.77 | Q8: 1488.5 | R8: Não OK | S8: Não OK | T8: =VLOOKUP(Tabela2[[#This Row],[Cliente]],Setor!$C$2:$F$1606,4,0) -> SUPERMERCADO SKINAO | U8: =VLOOKUP(Tabela2[[#This Row],[Cliente]],Setor!$C:$AU,45,0) -> 501 | V8: =_xlfn.XLOOKUP(Tabela2[[#This Row],[Setor]],AD:AD,AE:AE) -> Fredson | W8: =IF(Tabela2[[#This Row],[Meta Unit.]]=2,"SEISCENTOS","LITRINHO") -> LITRINHO | X8: =Tabela2[[#This Row],[Vol. Real Cx Mensal]] -> 15 | Y8: =(Tabela2[[#This Row],[Caixas Comodatadas]]*Tabela2[[#This Row],[Meta Unit.]])-Tabela2[[#This Row],[Comprou]] -> 60 | Z8: =IF(Tabela2[[#This Row],[Tipo de Vasilhame]] = "LITRINHO",1.5*Tabela2[[#This Row],[Caixas Comodatadas]],Tabela2[[#This Row],[Caixas Comodatadas]]*2) -> 75 | AA8: =IFERROR(IF(OR(FIND("OK", Tabela2[[#This Row],[Tipo Giro Mensal]]) > 0), IF(Tabela2[[#This Row],[Comprou]]/$AH$2*30 > Tabela2[[#This Row],[Meta]], "BATE", "ABAIXO"), "-"),"-") -> ABAIXO | AD8: 500 | AE8: Jaissa
A9: 407 | B9: JOSE JONAS DOS SANTOS | C9: Cerveja 1/2 | D9: 30 | E9: 44.85 | F9: 650 | G9: 4.81 | H9: 0 | I9: 0 | J9: 0 | K9: 0 | L9: 1.5 | M9: 296156 | N9: GARRAFEIRA PLAST,23 GFA 300ML,AZUL | O9: 30 | P9: 29.77 | Q9: 893.1 | R9: OK | S9: Zero | T9: =VLOOKUP(Tabela2[[#This Row],[Cliente]],Setor!$C$2:$F$1606,4,0) -> JOSE JONAS CURRAL V | U9: =VLOOKUP(Tabela2[[#This Row],[Cliente]],Setor!$C:$AU,45,0) -> 501 | V9: =_xlfn.XLOOKUP(Tabela2[[#This Row],[Setor]],AD:AD,AE:AE) -> Fredson | W9: =IF(Tabela2[[#This Row],[Meta Unit.]]=2,"SEISCENTOS","LITRINHO") -> LITRINHO | X9: =Tabela2[[#This Row],[Vol. Real Cx Mensal]] -> 0 | Y9: =(Tabela2[[#This Row],[Caixas Comodatadas]]*Tabela2[[#This Row],[Meta Unit.]])-Tabela2[[#This Row],[Comprou]] -> 45 | Z9: =IF(Tabela2[[#This Row],[Tipo de Vasilhame]] = "LITRINHO",1.5*Tabela2[[#This Row],[Caixas Comodatadas]],Tabela2[[#This Row],[Caixas Comodatadas]]*2) -> 45 | AA9: =IFERROR(IF(OR(FIND("OK", Tabela2[[#This Row],[Tipo Giro Mensal]]) > 0), IF(Tabela2[[#This Row],[Comprou]]/$AH$2*30 > Tabela2[[#This Row],[Meta]], "BATE", "ABAIXO"), "-"),"-") -> - | AD9: 101 | AE9: Fredson
A10: 876 | B10: M EAMP | C10: Cerveja 1/1 | D10: 6 | E10: 22.17 | F10: 154 | G10: 4.28 | H10: 1.58 | I10: 11 | J10: 0.92 | K10: 13.75 | L10: 2 | M10: 30491 | N10: GARRAFEIRA PLAST,24 GFA 600ML,SKOL,C/1, | O10: 6 | P10: 43.86 | Q10: 263.16 | R10: OK | S10: Não OK | T10: =VLOOKUP(Tabela2[[#This Row],[Cliente]],Setor!$C$2:$F$1606,4,0) -> S5 - REST LUA CHEIA | U10: =VLOOKUP(Tabela2[[#This Row],[Cliente]],Setor!$C:$AU,45,0) -> 500 | V10: =_xlfn.XLOOKUP(Tabela2[[#This Row],[Setor]],AD:AD,AE:AE) -> Jaissa | W10: =IF(Tabela2[[#This Row],[Meta Unit.]]=2,"SEISCENTOS","LITRINHO") -> SEISCENTOS | X10: =Tabela2[[#This Row],[Vol. Real Cx Mensal]] -> 11 | Y10: =(Tabela2[[#This Row],[Caixas Comodatadas]]*Tabela2[[#This Row],[Meta Unit.]])-Tabela2[[#This Row],[Comprou]] -> 1 | Z10: =IF(Tabela2[[#This Row],[Tipo de Vasilhame]] = "LITRINHO",1.5*Tabela2[[#This Row],[Caixas Comodatadas]],Tabela2[[#This Row],[Caixas Comodatadas]]*2) -> 12 | AA10: =IFERROR(IF(OR(FIND("OK", Tabela2[[#This Row],[Tipo Giro Mensal]]) > 0), IF(Tabela2[[#This Row],[Comprou]]/$AH$2*30 > Tabela2[[#This Row],[Meta]], "BATE", "ABAIXO"), "-"),"-") -> ABAIXO | AD10: 102 | AE10: Fredson
A11: 2918 | B11: JOAO VICTOR DO NASCIMENTO BRANDAO | C11: Cerveja 1/2 | D11: 10 | E11: 6.55 | F11: 95 | G11: 2.11 | H11: 0.34 | I11: 5 | J11: 0.33 | K11: 6.25 | L11: 1.5 | M11: 296156 | N11: GARRAFEIRA PLAST,23 GFA 300ML,AZUL | O11: 10 | P11: 29.77 | Q11: 297.7 | R11: OK | S11: Não OK | T11: =VLOOKUP(Tabela2[[#This Row],[Cliente]],Setor!$C$2:$F$1606,4,0) -> CHINA ESPETO | U11: =VLOOKUP(Tabela2[[#This Row],[Cliente]],Setor!$C:$AU,45,0) -> 501 | V11: =_xlfn.XLOOKUP(Tabela2[[#This Row],[Setor]],AD:AD,AE:AE) -> Fredson | W11: =IF(Tabela2[[#This Row],[Meta Unit.]]=2,"SEISCENTOS","LITRINHO") -> LITRINHO | X11: =Tabela2[[#This Row],[Vol. Real Cx Mensal]] -> 5 | Y11: =(Tabela2[[#This Row],[Caixas Comodatadas]]*Tabela2[[#This Row],[Meta Unit.]])-Tabela2[[#This Row],[Comprou]] -> 10 | Z11: =IF(Tabela2[[#This Row],[Tipo de Vasilhame]] = "LITRINHO",1.5*Tabela2[[#This Row],[Caixas Comodatadas]],Tabela2[[#This Row],[Caixas Comodatadas]]*2) -> 15 | AA11: =IFERROR(IF(OR(FIND("OK", Tabela2[[#This Row],[Tipo Giro Mensal]]) > 0), IF(Tabela2[[#This Row],[Comprou]]/$AH$2*30 > Tabela2[[#This Row],[Meta]], "BATE", "ABAIXO"), "-"),"-") -> ABAIXO | AD11: 104 | AE11: Fredson
A12: 3105 | B12: MANOEL RODRIGO SILVA ROCHA | C12: Cerveja 1/1 | D12: 2 | E12: 3.88 | F12: 27 | G12: 2.25 | H12: 0.28 | I12: 2 | J12: 0.5 | K12: 2.5 | L12: 2 | M12: 30491 | N12: GARRAFEIRA PLAST,24 GFA 600ML,SKOL,C/1, | O12: 2 | P12: 43.86 | Q12: 87.72 | R12: OK | S12: Não OK | T12: =VLOOKUP(Tabela2[[#This Row],[Cliente]],Setor!$C$2:$F$1606,4,0) -> BARRACA POR DO SOL | U12: =VLOOKUP(Tabela2[[#This Row],[Cliente]],Setor!$C:$AU,45,0) -> 104 | V12: =_xlfn.XLOOKUP(Tabela2[[#This Row],[Setor]],AD:AD,AE:AE) -> Fredson | W12: =IF(Tabela2[[#This Row],[Meta Unit.]]=2,"SEISCENTOS","LITRINHO") -> SEISCENTOS | X12: =Tabela2[[#This Row],[Vol. Real Cx Mensal]] -> 2 | Y12: =(Tabela2[[#This Row],[Caixas Comodatadas]]*Tabela2[[#This Row],[Meta Unit.]])-Tabela2[[#This Row],[Comprou]] -> 2 | Z12: =IF(Tabela2[[#This Row],[Tipo de Vasilhame]] = "LITRINHO",1.5*Tabela2[[#This Row],[Caixas Comodatadas]],Tabela2[[#This Row],[Caixas Comodatadas]]*2) -> 4 | AA12: =IFERROR(IF(OR(FIND("OK", Tabela2[[#This Row],[Tipo Giro Mensal]]) > 0), IF(Tabela2[[#This Row],[Comprou]]/$AH$2*30 > Tabela2[[#This Row],[Meta]], "BATE", "ABAIXO"), "-"),"-") -> ABAIXO | AD12: 501 | AE12: Fredson
A13: 3877 | B13: LE CHARME JERICOACOARA LTDA | C13: Cerveja 1/1 | D13: 20 | E13: 4.46 | F13: 31 | G13: 0.26 | H13: 0.72 | I13: 5 | J13: 0.13 | K13: 6.25 | L13: 2 | M13: 899599 | N13: GARRAFEIRA PLAST,24 GFA 600ML,,,, | O13: 20 | P13: 20 | Q13: 400 | R13: Não OK | S13: Não OK | T13: =VLOOKUP(Tabela2[[#This Row],[Cliente]],Setor!$C$2:$F$1606,4,0) -> LE CHARME JERICOACOA | U13: =VLOOKUP(Tabela2[[#This Row],[Cliente]],Setor!$C:$AU,45,0) -> 106 | V13: =_xlfn.XLOOKUP(Tabela2[[#This Row],[Setor]],AD:AD,AE:AE) -> Jaissa | W13: =IF(Tabela2[[#This Row],[Meta Unit.]]=2,"SEISCENTOS","LITRINHO") -> SEISCENTOS | X13: =Tabela2[[#This Row],[Vol. Real Cx Mensal]] -> 5 | Y13: =(Tabela2[[#This Row],[Caixas Comodatadas]]*Tabela2[[#This Row],[Meta Unit.]])-Tabela2[[#This Row],[Comprou]] -> 35 | Z13: =IF(Tabela2[[#This Row],[Tipo de Vasilhame]] = "LITRINHO",1.5*Tabela2[[#This Row],[Caixas Comodatadas]],Tabela2[[#This Row],[Caixas Comodatadas]]*2) -> 40 | AA13: =IFERROR(IF(OR(FIND("OK", Tabela2[[#This Row],[Tipo Giro Mensal]]) > 0), IF(Tabela2[[#This Row],[Comprou]]/$AH$2*30 > Tabela2[[#This Row],[Meta]], "BATE", "ABAIXO"), "-"),"-") -> ABAIXO
A14: 3891 | B14: IERY MARIA ARAUJO OSTERNO CAVALCANTE | C14: Cerveja 1/1 | D14: 32 | E14: 1.15 | F14: 8 | G14: 0.04 | H14: 0.72 | I14: 5 | J14: 0.08 | K14: 6.25 | L14: 2 | M14: 899599 | N14: GARRAFEIRA PLAST,24 GFA 600ML,,,, | O14: 32 | P14: 20 | Q14: 640 | R14: Não OK | S14: Não OK | T14: =VLOOKUP(Tabela2[[#This Row],[Cliente]],Setor!$C$2:$F$1606,4,0) -> CANDIEIRO BAR E REST | U14: =VLOOKUP(Tabela2[[#This Row],[Cliente]],Setor!$C:$AU,45,0) -> 102 | V14: =_xlfn.XLOOKUP(Tabela2[[#This Row],[Setor]],AD:AD,AE:AE) -> Fredson | W14: =IF(Tabela2[[#This Row],[Meta Unit.]]=2,"SEISCENTOS","LITRINHO") -> SEISCENTOS | X14: =Tabela2[[#This Row],[Vol. Real Cx Mensal]] -> 5 | Y14: =(Tabela2[[#This Row],[Caixas Comodatadas]]*Tabela2[[#This Row],[Meta Unit.]])-Tabela2[[#This Row],[Comprou]] -> 59 | Z14: =IF(Tabela2[[#This Row],[Tipo de Vasilhame]] = "LITRINHO",1.5*Tabela2[[#This Row],[Caixas Comodatadas]],Tabela2[[#This Row],[Caixas Comodatadas]]*2) -> 64 | AA14: =IFERROR(IF(OR(FIND("OK", Tabela2[[#This Row],[Tipo Giro Mensal]]) > 0), IF(Tabela2[[#This Row],[Comprou]]/$AH$2*30 > Tabela2[[#This Row],[Meta]], "BATE", "ABAIXO"), "-"),"-") -> ABAIXO
T15: =VLOOKUP(Tabela2[[#This Row],[Cliente]],Setor!$C$2:$F$1606,4,0) -> #N/A | U15: =VLOOKUP(Tabela2[[#This Row],[Cliente]],Setor!$C:$AU,45,0) -> #N/A | V15: =_xlfn.XLOOKUP(Tabela2[[#This Row],[Setor]],AD:AD,AE:AE) -> #N/A | W15: =IF(Tabela2[[#This Row],[Meta Unit.]]=2,"SEISCENTOS","LITRINHO") -> LITRINHO | X15: =Tabela2[[#This Row],[Vol. Real Cx Mensal]] -> 0 | Y15: =(Tabela2[[#This Row],[Caixas Comodatadas]]*Tabela2[[#This Row],[Meta Unit.]])-Tabela2[[#This Row],[Comprou]] -> 0 | Z15: =IF(Tabela2[[#This Row],[Tipo de Vasilhame]] = "LITRINHO",1.5*Tabela2[[#This Row],[Caixas Comodatadas]],Tabela2[[#This Row],[Caixas Comodatadas]]*2) -> 0 | AA15: =IFERROR(IF(OR(FIND("OK", Tabela2[[#This Row],[Tipo Giro Mensal]]) > 0), IF(Tabela2[[#This Row],[Comprou]]/$AH$2*30 > Tabela2[[#This Row],[Meta]], "BATE", "ABAIXO"), "-"),"-") -> -
T16: =VLOOKUP(Tabela2[[#This Row],[Cliente]],Setor!$C$2:$F$1606,4,0) -> #N/A | U16: =VLOOKUP(Tabela2[[#This Row],[Cliente]],Setor!$C:$AU,45,0) -> #N/A | V16: =_xlfn.XLOOKUP(Tabela2[[#This Row],[Setor]],AD:AD,AE:AE) -> #N/A | W16: =IF(Tabela2[[#This Row],[Meta Unit.]]=2,"SEISCENTOS","LITRINHO") -> LITRINHO | X16: =Tabela2[[#This Row],[Vol. Real Cx Mensal]] -> 0 | Y16: =(Tabela2[[#This Row],[Caixas Comodatadas]]*Tabela2[[#This Row],[Meta Unit.]])-Tabela2[[#This Row],[Comprou]] -> 0 | Z16: =IF(Tabela2[[#This Row],[Tipo de Vasilhame]] = "LITRINHO",1.5*Tabela2[[#This Row],[Caixas Comodatadas]],Tabela2[[#This Row],[Caixas Comodatadas]]*2) -> 0 | AA16: =IFERROR(IF(OR(FIND("OK", Tabela2[[#This Row],[Tipo Giro Mensal]]) > 0), IF(Tabela2[[#This Row],[Comprou]]/$AH$2*30 > Tabela2[[#This Row],[Meta]], "BATE", "ABAIXO"), "-"),"-") -> -
R32: =9/183 -> 0.049180328

Sheet Setor
A1: Empresa | B1: Filial | C1: Cód PDV | D1: Documento | E1: Situação na RF | F1: Nome Fantasia | G1: Razão Social | H1: Endereço | I1: Complemento | J1: Bairro | K1: Cidade | L1: UF | M1: CEP | N1: Telefone(s) | O1: Categoria | P1: Cód Rede | Q1: Nome Rede | R1: Classe Risco Atual | S1: Pontuação Score | T1: Modelo Score | U1: Segmento Score | V1: Limite de Crédito | W1: Limite de Crédito Usado | X1: Limite de Crédito Disponível | Y1: Prazo Atual | Z1: Prazo Máximo Matriz | AA1: Maior Prazo por Título | AB1: Atraso Médio | AC1: Perc Pgto em Atraso | AD1: Possui Comodato | AE1: Situação Documentação | AF1: Data de Cadastro | AG1: Data da Última Compra | AH1: Compra Média | AI1: Maior Compra | AJ1: Acumulado de Vendas | AK1: Títulos Pendentes | AL1: Títulos à Vencer | AM1: Perc CR à Vencer (M-1) | AN1: Data de Envio Serasa | AO1: Data de Retorno Serasa | AP1: Cód EG | AQ1: Cliente em Inativação | AR1: Motivo Lista de Restrições | AS1: Tipo de Pessoa | AT1: Status do PDV | AU1: Setor VDE | AV1: Área VDE | AW1: GV VDE | AX1: Data Início da Visita VDE | AY1: Dia de Visita do VDE | AZ1: Data da Prox Visita VDE | BA1: Perc Positivação VDE(Mês) | BB1: Perc Positivação VDE(TRI) | BC1: Perc GPS VDE(Mês) | BD1: Setor VDI | BE1: Área VDI | BF1: GV VDI | BG1: Data Início da Visita VDI | BH1: Dia de Visita do VDI | BI1: Data da Prox Visita VDI | BJ1: Perc Positivação VDI(Mês) | BK1: Perc Positivação VDI(TRI) | BL1: Perc Contatos VDI(Mês) | BM1: Prazo Médio Ponderado à Prazo (M-1) | BN1: Prazo Médio Ponderado (M-1) | BO1: Faturamento à Prazo (M-1) | BP1: Faturamento DH (M-1) | BQ1: Faturamento Total (M-1) | BR1: CR a Vencer (M-1) | BS1: Prazo Médio Ponderado à Prazo (Mês) | BT1: Prazo Médio Ponderado (Mês) | BU1: Faturamento à Prazo (Mês) | BV1: Faturamento DH (Mês) | BW1: Faturamento Total (Mês) | BX1: CR a Vencer (Mês) | BY1: Perc CR a Vencer (Mês) | BZ1: Perc Atraso(6 meses) | CA1: Maior Atraso(6 meses) | CB1: Média Faturamento(3 meses) | CC1: Segmento NGE
A2: 345 | B2: 2 | C2: 1 | D2: 906.489.003-04 | F2: AGUA NA BOCA | G2: ELAINE CRISTINA RIOS FONTELES | H2: R R GUIDO OSTERNUO SN | J2: CENTRO | K2: MARCO | L2: CE | M2: 62.560-000 | N2: 88 99959-0105 | O2: ARMAZEM/MERCEARIA | P2: 0 | R2: 6 | S2: 38 | V2: 0 | W2: 0 | X2: 0 | Y2: 0 | Z2: 0 | AA2: 0 | AB2: 0 | AC2: 0 | AD2: Nao | AE2: Nao | AF2: 45518 | AG2: 46011 | AH2: 1112.78 | AI2: 1622.79 | AJ2: 5563.92 | AK2: 0 | AL2: 0 | AM2: 0 | AQ2: N | AS2: Fisica | AT2: Ativo | AU2: 102 | AV2: 10 | AW2: 1 | AX2: 45999 | AY2: SEG/ | AZ2: 46027 | BA2: 0 | BB2: 0 | BC2: 0 | BD2: 700 | BE2: 70 | BF2: 9 | BG2: 45536 | BH2: DOM/ | BI2: 46026 | BJ2: 0 | BK2: 0 | BL2: 0 | BM2: 0 | BN2: 0 | BO2: 0 | BP2: 3932.24 | BQ2: 3932.24 | BR2: 0 | BS2: 0 | BT2: 0 | BU2: 0 | BV2: 803.06 | BW2: 803.06 | BX2: 0 | BY2: 0 | BZ2: 0 | CA2: 0 | CB2: 1868.43 | CC2: TRAD
A3: 345 | B3: 2 | C3: 3 | D3: 21.261.228/0001-05 | F3: DEP RAIMUNDO MONTE | G3: TRES Y COMERCIAL DE ALIMENTOS | H3: R R GOVERNADOR RAUL BARBOSA 553 55553 | J3: CENTRO | K3: MARCO | L3: CE | M3: 62.560-000 | N3: 88 3664-1550 | O3: DEPOSITO DE BEBIDAS | P3: 0 | R3: 3 | S3: 88 | V3: 14700 | W3: 0 | X3: 14700 | Y3: 7 | Z3: 0 | AA3: 0 | AB3: 0 | AC3: 0 | AD3: Nao | AE3: Nao | AF3: 45518 | AG3: 46020 | AH3: 9902 | AI3: 21446 | AJ3: 128726 | AK3: 0 | AL3: 0 | AM3: 0 | AQ3: N | AS3: Juridica | AT3: Ativo | AU3: 501 | AV3: 10 | AW3: 1 | AX3: 45947 | AY3: SEX/ | AZ3: 46024 | BA3: 0 | BB3: 0 | BC3: 0 | BD3: 700 | BE3: 70 | BF3: 9 | BG3: 45536 | BH3: DOM/ | BI3: 46026 | BJ3: 0 | BK3: 0 | BL3: 0 | BM3: 0 | BN3: 0 | BO3: 0 | BP3: 37472.35 | BQ3: 37472.35 | BR3: 0 | BS3: 0 | BT3: 0 | BU3: 0 | BV3: 66554.5 | BW3: 66554.5 | BX3: 0 | BY3: 0 | BZ3: 0 | CA3: 0 | CB3: 34231.88 | CC3: SUB
A4: 345 | B4: 2 | C4: 4 | D4: 680.078.413-34 | F4: REST DA ELENITA TRI | G4: MARIA ELENITA LEITE | H4: RUA AV TRIANGULO DO MARCO 10 | J4: TRIANGULO DO MARCO | K4: MARCO | L4: CE | M4: 62.560-000 | N4: 88 3664-4053 | O4: REST./PIZZARIA/CHURR | P4: 0 | R4: 6 | S4: 36 | V4: 0 | W4: 0 | X4: 0 | Y4: 0 | Z4: 0 | AA4: 0 | AB4: 0 | AC4: 0 | AD4: Nao | AE4: Nao | AF4: 45518 | AG4: 46020 | AH4: 768.19 | AI4: 1269.28 | AJ4: 9986.55 | AK4: 0 | AL4: 0 | AM4: 0 | AQ4: N | AS4: Fisica | AT4: Ativo | AU4: 102 | AV4: 10 | AW4: 1 | AX4: 45815 | AY4: SAB/ | AZ4: 46025 | BA4: 0 | BB4: 0 | BC4: 0 | BD4: 700 | BE4: 70 | BF4: 9 | BG4: 45536 | BH4: DOM/ | BI4: 46026 | BJ4: 0 | BK4: 0 | BL4: 0 | BM4: 0 | BN4: 0 | BO4: 0 | BP4: 3441.49 | BQ4: 3441.49 | BR4: 0 | BS4: 0 | BT4: 0 | BU4: 0 | BV4: 3654.2 | BW4: 3654.2 | BX4: 0 | BY4: 0 | BZ4: 0 | CA4: 0 | CB4: 3049.15 | CC4: Rota
A5: 345 | B5: 2 | C5: 5 | D5: 547.792.353-91 | F5: BAR DO 100 MARCO | G5: JOAO VALNEY SILVA | H5: RUA R JOSE MARIA FARIAS 720 | J5: CENTRO | K5: MARCO | L5: CE | M5: 62.560-000 | N5: 88 99600-2082 | O5: BAR/BARZINHO | P5: 0 | R5: 6 | S5: 36 | V5: 0 | W5: 0 | X5: 0 | Y5: 0 | Z5: 0 | AA5: 0 | AB5: 0 | AC5: 0 | AD5: Nao | AE5: Nao | AF5: 45518 | AG5: 46018 | AH5: 515.09 | AI5: 869.76 | AJ5: 5666.02 | AK5: 0 | AL5: 0 | AM5: 0 | AQ5: N | AS5: Fisica | AT5: Ativo | AU5: 102 | AV5: 10 | AW5: 1 | AX5: 45847 | AY5: QUA/ | AZ5: 46022 | BA5: 0 | BB5: 0 | BC5: 0 | BD5: 700 | BE5: 70 | BF5: 9 | BG5: 45536 | BH5: DOM/ | BI5: 46026 | BJ5: 0 | BK5: 0 | BL5: 0 | BM5: 0 | BN5: 0 | BO5: 0 | BP5: 2066.7 | BQ5: 2066.7 | BR5: 0 | BS5: 0 | BT5: 0 | BU5: 0 | BV5: 1513.88 | BW5: 1513.88 | BX5: 0 | BY5: 0 | BZ5: 0 | CA5: 0 | CB5: 2068 | CC5: Rota
A6: 345 | B6: 2 | C6: 7 | D6: 923.862.373-20 | F6: MERC DO PAULO MARCO | G6: PAULO CESAR SOUZA | H6: RUA R VIRGILIO TAVORA 1713 | J6: ALEMAES | K6: MARCO | L6: CE | M6: 62.560-000 | N6: 88 99915-7756 | O6: ARMAZEM/MERCEARIA | P6: 0 | R6: 6 | S6: 41 | V6: 0 | W6: 0 | X6: 0 | Y6: 0 | Z6: 0 | AA6: 0 | AB6: 0 | AC6: 0 | AD6: Nao | AE6: Nao | AF6: 45518 | AG6: 46021 | AH6: 2542.74 | AI6: 9173.85 | AJ6: 35598.46 | AK6: 0 | AL6: 0 | AM6: 0 | AQ6: N | AS6: Fisica | AT6: Ativo | AU6: 102 | AV6: 10 | AW6: 1 | AX6: 45847 | AY6: QUA/ | AZ6: 46022 | BA6: 0 | BB6: 0 | BC6: 0 | BD6: 700 | BE6: 70 | BF6: 9 | BG6: 45536 | BH6: DOM/ | BI6: 46026 | BJ6: 0 | BK6: 0 | BL6: 0 | BM6: 0 | BN6: 0 | BO6: 0 | BP6: 8278.89 | BQ6: 8278.89 | BR6: 0 | BS6: 0 | BT6: 0 | BU6: 0 | BV6: 15164.36 | BW6: 15814.36 | BX6: 0 | BY6: 0 | BZ6: 0 | CA6: 0 | CB6: 14196.53 | CC6: TRAD
A7: 345 | B7: 2 | C7: 9 | D7: 048.352.613-48 | F7: CHUR MANOEL FRANKLIN | G7: JONAS FRANKLIM SILVA MELO | H7: EST EST TRIANGULO DE MARCO SN | J7: TRIANGULO DO MARCO | K7: MARCO | L7: CE | M7: 62.560-000 | N7: 88 3664-4009 | O7: BAR/BARZINHO | P7: 0 | R7: 6 | S7: 36 | V7: 0 | W7: 0 | X7: 0 | Y7: 0 | Z7: 0 | AA7: 0 | AB7: 0 | AC7: 0 | AD7: Nao | AE7: Nao | AF7: 45518 | AG7: 46019 | AH7: 205.74 | AI7: 390.17 | AJ7: 1851.69 | AK7: 0 | AL7: 0 | AM7: 0 | AQ7: N | AS7: Fisica | AT7: Ativo | AU7: 102 | AV7: 10 | AW7: 1 | AX7: 45966 | AY7: QUA/ | AZ7: 46022 | BA7: 0 | BB7: 0 | BC7: 0 | BD7: 700 | BE7: 70 | BF7: 9 | BG7: 45536 | BH7: DOM/ | BI7: 46026 | BJ7: 0 | BK7: 0 | BL7: 0 | BM7: 0 | BN7: 0 | BO7: 0 | BP7: 800.58 | BQ7: 800.58 | BR7: 0 | BS7: 0 | BT7: 0 | BU7: 0 | BV7: 763.67 | BW7: 763.67 | BX7: 0 | BY7: 0 | BZ7: 0 | CA7: 0 | CB7: 508.55 | CC7: Rota
A8: 345 | B8: 2 | C8: 12 | D8: 027.816.953-86 | F8: S5 - DEP SAO FRANCIS | G8: JOSE GLEISON ALVES | H8: R R PADRE APOLIANO SN | J8: ALEMAES | K8: MARCO | L8: CE | M8: 62.560-000 | N8: 08 89634-2862 | O8: BAR/BARZINHO | P8: 0 | R8: 6 | S8: 37 | V8: 0 | W8: 0 | X8: 0 | Y8: 0 | Z8: 0 | AA8: 0 | AB8: 0 | AC8: 0 | AD8: Nao | AE8: Nao | AF8: 45518 | AG8: 46020 | AH8: 4458.68 | AI8: 8936.87 | AJ8: 49045.51 | AK8: 0 | AL8: 0 | AM8: 0 | AQ8: N | AS8: Fisica | AT8: Ativo | AU8: 102 | AV8: 10 | AW8: 1 | AX8: 45843 | AY8: SAB/ | AZ8: 46025 | BA8: 0 | BB8: 0 | BC8: 0 | BD8: 700 | BE8: 70 | BF8: 9 | BG8: 45536 | BH8: DOM/ | BI8: 46026 | BJ8: 0 | BK8: 0 | BL8: 0 | BM8: 0 | BN8: 0 | BO8: 0 | BP8: 19076.56 | BQ8: 19076.56 | BR8: 0 | BS8: 0 | BT8: 0 | BU8: 0 | BV8: 21277.89 | BW8: 21277.89 | BX8: 0 | BY8: 0 | BZ8: 0 | CA8: 0 | CB8: 12789.82 | CC8: SUB
A9: 345 | B9: 2 | C9: 20 | D9: 907.050.333-68 | F9: MARCOS ANDRE | G9: MARCOS ANDRE GOMES | H9: R R FRANCISCO TEoFILO DA ROCHA SN | J9: ALEMAES | K9: MARCO | L9: CE | M9: 62.560-000 | N9: 88 99916-7948 | O9: ARMAZEM/MERCEARIA | P9: 0 | R9: 6 | S9: 39 | V9: 0 | W9: 0 | X9: 0 | Y9: 0 | Z9: 0 | AA9: 0 | AB9: 0 | AC9: 0 | AD9: Nao | AE9: Nao | AF9: 45518 | AG9: 46002 | AH9: 337.21 | AI9: 399.57 | AJ9: 674.42 | AK9: 0 | AL9: 0 | AM9: 0 | AQ9: N | AS9: Fisica | AT9: Ativo | AU9: 102 | AV9: 10 | AW9: 1 | AX9: 45847 | AY9: QUA/ | AZ9: 46022 | BA9: 0 | BB9: 0 | BC9: 0 | BD9: 700 | BE9: 70 | BF9: 9 | BG9: 45536 | BH9: DOM/ | BI9: 46026 | BJ9: 0 | BK9: 0 | BL9: 0 | BM9: 0 | BN9: 0 | BO9: 0 | BP9: 274.85 | BQ9: 274.85 | BR9: 0 | BS9: 0 | BT9: 0 | BU9: 0 | BV9: 399.57 | BW9: 399.57 | BX9: 0 | BY9: 0 | BZ9: 0 | CA9: 0 | CB9: 536.82 | CC9: TRAD
A10: 345 | B10: 2 | C10: 21 | D10: 14.420.595/0001-49 | F10: LANCH D GUSTE 99 | G10: CLAUDIA CRISTINA SILVA SILVEIRA ME. | H10: RUA R PADRE APOLIANO 357 | J10: CENTRO | K10: MARCO | L10: CE | M10: 62.560-000 | N10: 88 99915-2535 | O10: LANCHONETE/PASTELARI | P10: 0 | R10: 6 | S10: 40 | V10: 0 | W10: 0 | X10: 0 | Y10: 0 | Z10: 0 | AA10: 0 | AB10: 0 | AC10: 0 | AD10: Nao | AE10: Nao | AF10: 45518 | AG10: 46014 | AH10: 204.81 | AI10: 279.24 | AJ10: 1024.09 | AK10: 0 | AL10: 0 | AM10: 0 | AQ10: N | AS10: Juridica | AT10: Ativo | AU10: 102 | AV10: 10 | AW10: 1 | AX10: 45810 | AY10: SEG/ | AZ10: 46027 | BA10: 0 | BB10: 0 | BC10: 0 | BD10: 700 | BE10: 70 | BF10: 9 | BG10: 45536 | BH10: DOM/ | BI10: 46026 | BJ10: 0 | BK10: 0 | BL10: 0 | BM10: 0 | BN10: 0 | BO10: 0 | BP10: 188.15 | BQ10: 188.15 | BR10: 0 | BS10: 0 | BT10: 0 | BU10: 0 | BV10: 477.84 | BW10: 477.84 | BX10: 0 | BY10: 0 | BZ10: 0 | CA10: 0 | CB10: 182.08 | CC10: Rota
A11: 345 | B11: 2 | C11: 23 | D11: 907.205.123-87 | F11: MARIA ELIDENE | G11: MARIA ELIDENE DE SOUZA | H11: R R TRIANGULO DO MARCO SN | J11: TRIANGULO DO MARCO | K11: MARCO | L11: CE | M11: 62.560-000 | N11: 88 99964-1443 | O11: MINIMERCADO | P11: 0 | R11: 6 | S11: 41 | V11: 0 | W11: 0 | X11: 0 | Y11: 0 | Z11: 0 | AA11: 0 | AB11: 0 | AC11: 0 | AD11: Nao | AE11: Nao | AF11: 45518 | AG11: 46020 | AH11: 129.67 | AI11: 217.83 | AJ11: 1296.79 | AK11: 0 | AL11: 0 | AM11: 0 | AQ11: N | AS11: Fisica | AT11: Ativo | AU11: 102 | AV11: 10 | AW11: 1 | AX11: 45815 | AY11: SAB/ | AZ11: 46025 | BA11: 0 | BB11: 0 | BC11: 0 | BD11: 700 | BE11: 70 | BF11: 9 | BG11: 45536 | BH11: DOM/ | BI11: 46026 | BJ11: 0 | BK11: 0 | BL11: 0 | BM11: 0 | BN11: 0 | BO11: 0 | BP11: 229.2 | BQ11: 229.2 | BR11: 0 | BS11: 0 | BT11: 0 | BU11: 0 | BV11: 743.81 | BW11: 743.81 | BX11: 0 | BY11: 0 | BZ11: 0 | CA11: 0 | CB11: 302.65 | CC11: Rota
A12: 345 | B12: 2 | C12: 27 | D12: 682.119.703-25 | F12: MERC ROGENIO SANTA | G12: JOSE ROGENIO DE FREITAS | H12: VIL R SANTA ROSA 144 | J12: SANTA ROSA | K12: MARCO | L12: CE | M12: 62.560-000 | N12: 88 99640-1663 | O12: ARMAZEM/MERCEARIA | P12: 0 | R12: 6 | S12: 41 | V12: 0 | W12: 0 | X12: 0 | Y12: 0 | Z12: 0 | AA12: 0 | AB12: 0 | AC12: 0 | AD12: Nao | AE12: Nao | AF12: 45518 | AG12: 46021 | AH12: 1165.82 | AI12: 2855.54 | AJ12: 10492.45 | AK12: 0 | AL12: 0 | AM12: 0 | AQ12: N | AS12: Fisica | AT12: Ativo | AU12: 102 | AV12: 10 | AW12: 1 | AX12: 45537 | AY12: SEG/ | AZ12: 46027 | BA12: 0 | BB12: 0 | BC12: 0 | BD12: 700 | BE12: 70 | BF12: 9 | BG12: 45536 | BH12: DOM/ | BI12: 46026 | BJ12: 0 | BK12: 0 | BL12: 0 | BM12: 0 | BN12: 0 | BO12: 0 | BP12: 1060.81 | BQ12: 1060.81 | BR12: 0 | BS12: 0 | BT12: 0 | BU12: 0 | BV12: 7370.28 | BW12: 7370.28 | BX12: 0 | BY12: 0 | BZ12: 0 | CA12: 0 | CB12: 3101.34 | CC12: TRAD
A13: 345 | B13: 2 | C13: 28 | D13: 645.481.123-91 | F13: MERC SANDRO | G13: SANDRO JOVINO FREITAS | H13: VIL DT BOM JESUS I 10 | J13: TRIANGULO DO MARCO | K13: MARCO | L13: CE | M13: 62.560-000 | N13: 66 0064-4003 | O13: ARMAZEM/MERCEARIA | P13: 0 | R13: 6 | S13: 41 | V13: 0 | W13: 0 | X13: 0 | Y13: 0 | Z13: 0 | AA13: 0 | AB13: 0 | AC13: 0 | AD13: Nao | AE13: Nao | AF13: 45518 | AG13: 46020 | AH13: 1537.44 | AI13: 3156.79 | AJ13: 13837.03 | AK13: 0 | AL13: 0 | AM13: 0 | AQ13: N | AS13: Fisica | AT13: Ativo | AU13: 102 | AV13: 10 | AW13: 1 | AX13: 45815 | AY13: SAB/ | AZ13: 46025 | BA13: 0 | BB13: 0 | BC13: 0 | BD13: 700 | BE13: 70 | BF13: 9 | BG13: 45536 | BH13: DOM/ | BI13: 46026 | BJ13: 0 | BK13: 0 | BL13: 0 | BM13: 0 | BN13: 0 | BO13: 0 | BP13: 3446.97 | BQ13: 3446.97 | BR13: 0 | BS13: 0 | BT13: 0 | BU13: 0 | BV13: 7834.51 | BW13: 7834.51 | BX13: 0 | BY13: 0 | BZ13: 0 | CA13: 0 | CB13: 2804.25 | CC13: TRAD
... A19: 345 | B19: 2 | C19: 57 | D19: 007.628.153-10 | F19: REST ROTA DOS SABORE | G19: FRANCISCO ERONDI ARAUJO | H19: R TRIANGULO DO MARCO SN | J19: TRIANGULO DO MARCO | K19: MARCO | L19: CE | M19: 62.560-000 | N19: 08 83664-2552 | O19: REST./PIZZARIA/CHURR | P19: 0 | R19: 6 | S19: 36 | V19: 0 | W19: 0 | X19: 0 | Y19: 0 | Z19: 0 | AA19: 0 | AB19: 0 | AC19: 0 | AD19: Nao | AE19: Nao | AF19: 45518 | AG19: 46011 | AH19: 2031.11 | AI19: 3101.78 | AJ19: 14217.79 | AK19: 0 | AL19: 0 | AM19: 0 | AQ19: N | AS19: Fisica | AT19: Ativo | AU19: 501 | AV19: 10 | AW19: 1 | AX19: 45856 | AY19: SEX/ | AZ19: 46024 | BA19: 0 | BB19: 0 | BC19: 0 | BD19: 700 | BE19: 70 | BF19: 9 | BG19: 45536 | BH19: DOM/ | BI19: 46026 | BJ19: 0 | BK19: 0 | BL19: 0 | BM19: 0 | BN19: 0 | BO19: 0 | BP19: 3268.16 | BQ19: 3268.16 | BR19: 0 | BS19: 0 | BT19: 0 | BU19: 0 | BV19: 5573.6 | BW19: 5573.6 | BX19: 0 | BY19: 0 | BZ19: 0 | CA19: 0 | CB19: 4175.82 | CC19: Rota
A20: 345 | B20: 2 | C20: 58 | D20: 048.702.003-09 | F20: DEP DE AGUAS JONAS | G20: FRANCISCO JONAS DE FREITAS | H20: R TRIANGULO DO MARCO 11 | J20: ALEMAES | K20: MARCO | L20: CE | M20: 62.560-000 | N20: 88 89731-3007 | O20: DEPOSITO DE BEBIDAS | P20: 0 | R20: 3 | S20: 85 | V20: 1294 | W20: 0 | X20: 1294 | Y20: 7 | Z20: 0 | AA20: 5 | AB20: 0 | AC20: 0 | AD20: Nao | AE20: Nao | AF20: 45518 | AG20: 46004 | AH20: 855.3 | AI20: 1680.9 | AJ20: 5131.84 | AK20: 0 | AL20: 0 | AM20: 0 | AQ20: N | AS20: Fisica | AT20: Ativo | AU20: 102 | AV20: 10 | AW20: 1 | AX20: 45926 | AY20: SEX/ | AZ20: 46024 | BA20: 0 | BB20: 0 | BC20: 0 | BD20: 999 | BE20: 99 | BF20: 9 | BJ20: 0 | BK20: 0 | BL20: 0 | BM20: 3 | BN20: 1.13 | BO20: 695.44 | BP20: 1146 | BQ20: 1841.44 | BR20: 695.44 | BS20: 5 | BT20: 2.52 | BU20: 848.4 | BV20: 832.5 | BW20: 1680.9 | BX20: 0 | BY20: 0 | BZ20: 0 | CA20: 0 | CB20: 1307.31 | CC20: SUB
A21: 345 | B21: 2 | C21: 59 | D21: 155.742.613-91 | F21: MERC MARJO | G21: FRANCISCO DE ASSIS DO NASCIMENTO | H21: R GOV RAUL BARBOSA SN | J21: CENTRO | K21: MARCO | L21: CE | M21: 62.560-000 | N21: 08 89752-2153 | O21: ARMAZEM/MERCEARIA | P21: 0 | R21: 6 | S21: 42 | V21: 0 | W21: 0 | X21: 0 | Y21: 0 | Z21: 0 | AA21: 0 | AB21: 0 | AC21: 0 | AD21: Nao | AE21: Nao | AF21: 45518 | AG21: 46017 | AH21: 146.92 | AI21: 194.94 | AJ21: 1175.38 | AK21: 0 | AL21: 0 | AM21: 0 | AQ21: N | AS21: Fisica | AT21: Ativo | AU21: 102 | AV21: 10 | AW21: 1 | AX21: 45847 | AY21: QUA/ | AZ21: 46022 | BA21: 0 | BB21: 0 | BC21: 0 | BD21: 700 | BE21: 70 | BF21: 9 | BG21: 45536 | BH21: DOM/ | BI21: 46026 | BJ21: 0 | BK21: 0 | BL21: 0 | BM21: 0 | BN21: 0 | BO21: 0 | BP21: 295.22 | BQ21: 295.22 | BR21: 0 | BS21: 0 | BT21: 0 | BU21: 0 | BV21: 355.8 | BW21: 355.8 | BX21: 0 | BY21: 0 | BZ21: 0 | CA21: 0 | CB21: 365.12 | CC21: TRAD
A22: 345 | B22: 2 | C22: 66 | D22: 069.418.613-98 | F22: MERC ISAIAS TRIANGU | G22: FRANCISCO ALEXSANDRO RIBEIRO | H22: VIL TRIANGULO DO MARCO 10 | J22: TRIANGULO DO MARCO | K22: MARCO | L22: CE | M22: 62.560-000 | N22: 08 89625-6704 | O22: ARMAZEM/MERCEARIA | P22: 0 | R22: 6 | S22: 39 | V22: 0 | W22: 0 | X22: 0 | Y22: 0 | Z22: 0 | AA22: 0 | AB22: 0 | AC22: 0 | AD22: Nao | AE22: Nao | AF22: 45518 | AG22: 46020 | AH22: 358.99 | AI22: 832.79 | AJ22: 1794.98 | AK22: 0 | AL22: 0 | AM22: 0 | AQ22: N | AS22: Fisica | AT22: Ativo | AU22: 102 | AV22: 10 | AW22: 1 | AX22: 45842 | AY22: SEX/ | AZ22: 46024 | BA22: 0 | BB22: 0 | BC22: 0 | BD22: 700 | BE22: 70 | BF22: 9 | BG22: 45536 | BH22: DOM/ | BI22: 46026 | BJ22: 0 | BK22: 0 | BL22: 0 | BM22: 0 | BN22: 0 | BO22: 0 | BP22: 455.15 | BQ22: 455.15 | BR22: 0 | BS22: 0 | BT22: 0 | BU22: 0 | BV22: 1076.61 | BW22: 1076.61 | BX22: 0 | BY22: 0 | BZ22: 0 | CA22: 0 | CB22: 296.4 | CC22: TRAD
A23: 345 | B23: 2 | C23: 68 | D23: 709.361.883-91 | F23: DEP FURTUOSO SANTA | G23: JOSE FURTUOSO DE FREITAS | H23: VIL SANTA ROSA 10 | J23: SANTA ROSA | K23: MARCO | L23: CE | M23: 62.560-000 | N23: 08 89922-5756 | O23: DEPOSITO DE BEBIDAS | P23: 0 | R23: 6 | S23: 41 | V23: 0 | W23: 0 | X23: 0 | Y23: 0 | Z23: 0 | AA23: 0 | AB23: 0 | AC23: 0 | AD23: Nao | AE23: Nao | AF23: 45518 | AG23: 46014 | AH23: 2203.32 | AI23: 5484 | AJ23: 24236.6 | AK23: 0 | AL23: 0 | AM23: 0 | AQ23: N | AS23: Fisica | AT23: Ativo | AU23: 102 | AV23: 10 | AW23: 1 | AX23: 45537 | AY23: SEG/ | AZ23: 46027 | BA23: 0 | BB23: 0 | BC23: 0 | BD23: 700 | BE23: 70 | BF23: 9 | BG23: 45536 | BH23: DOM/ | BI23: 46026 | BJ23: 0 | BK23: 0 | BL23: 0 | BM23: 0 | BN23: 0 | BO23: 0 | BP23: 6798.38 | BQ23: 6798.38 | BR23: 0 | BS23: 0 | BT23: 0 | BU23: 0 | BV23: 12381.07 | BW23: 12381.07 | BX23: 0 | BY23: 0 | BZ23: 0 | CA23: 0 | CB23: 6739.19 | CC23: SUB
A24: 345 | B24: 2 | C24: 69 | D24: 025.215.253-08 | F24: DEPOSITO TIAGO MARC | G24: MANOEL TIAGO LEITAO | H24: RUA MANOEL RODRIGUES 10 | J24: CENTRO | K24: MARCO | L24: CE | M24: 62.560-000 | N24: 08 89863-5800 | O24: DEPOSITO DE BEBIDAS | P24: 0 | R24: 6 | S24: 42 | V24: 0 | W24: 0 | X24: 0 | Y24: 0 | Z24: 0 | AA24: 0 | AB24: 0 | AC24: 0 | AD24: Nao | AE24: Nao | AF24: 45518 | AG24: 46020 | AH24: 1103 | AI24: 3559.93 | AJ24: 15442.07 | AK24: 0 | AL24: 0 | AM24: 0 | AQ24: N | AS24: Fisica | AT24: Ativo | AU24: 102 | AV24: 10 | AW24: 1 | AX24: 45810 | AY24: SEG/ | AZ24: 46027 | BA24: 0 | BB24: 0 | BC24: 0 | BD24: 700 | BE24: 70 | BF24: 9 | BG24: 45536 | BH24: DOM/ | BI24: 46026 | BJ24: 0 | BK24: 0 | BL24: 0 | BM24: 0 | BN24: 0 | BO24: 0 | BP24: 6278.64 | BQ24: 6278.64 | BR24: 0 | BS24: 0 | BT24: 0 | BU24: 0 | BV24: 4965.45 | BW24: 4965.45 | BX24: 0 | BY24: 0 | BZ24: 0 | CA24: 0 | CB24: 6303.61 | CC24: SUB
A25: 345 | B25: 2 | C25: 71 | D25: 038.646.553-31 | F25: DEP E ARMAZEM RD MA | G25: LEIDYANA CRISTINA SILVA SILVEIRA | H25: RUA 30 DE JULHO 207 | J25: CENTRO | K25: MARCO | L25: CE | M25: 62.560-000 | N25: 08 89685-2389 | O25: DEPOSITO DE BEBIDAS | P25: 0 | R25: 6 | S25: 42 | V25: 0 | W25: 0 | X25: 0 | Y25: 0 | Z25: 0 | AA25: 0 | AB25: 0 | AC25: 0 | AD25: Nao | AE25: Nao | AF25: 45518 | AG25: 46020 | AH25: 3692.35 | AI25: 12661.16 | AJ25: 44308.26 | AK25: 0 | AL25: 0 | AM25: 0 | AQ25: N | AS25: Fisica | AT25: Ativo | AU25: 501 | AV25: 10 | AW25: 1 | AX25: 45856 | AY25: SEX/ | AZ25: 46024 | BA25: 0 | BB25: 0 | BC25: 0 | BD25: 700 | BE25: 70 | BF25: 9 | BG25: 45536 | BH25: DOM/ | BI25: 46026 | BJ25: 0 | BK25: 0 | BL25: 0 | BM25: 0 | BN25: 0 | BO25: 0 | BP25: 21820.45 | BQ25: 21820.45 | BR25: 0 | BS25: 0 | BT25: 0 | BU25: 0 | BV25: 20553.61 | BW25: 20553.61 | BX25: 0 | BY25: 0 | BZ25: 0 | CA25: 0 | CB25: 20907.99 | CC25: SUB
A26: 345 | B26: 2 | C26: 75 | D26: 080.143.583-84 | F26: LANCHONET MAIS SABOR | G26: FRANCISCO JOEL DE FREITAS | H26: AV GUIDO OSTERNO 10 | J26: CENTRO | K26: MARCO | L26: CE | M26: 62.560-000 | N26: 88 89816-9737 | O26: LANCHONETE/PASTELARI | P26: 0 | R26: 3 | S26: 85 | V26: 1000 | W26: 0 | X26: 1000 | Y26: 7 | Z26: 0 | AA26: 0 | AB26: 0 | AC26: 0 | AD26: Nao | AE26: Nao | AF26: 45518 | AG26: 46009 | AH26: 302.65 | AI26: 711.6 | AJ26: 2421.25 | AK26: 0 | AL26: 0 | AM26: 0 | AQ26: N | AS26: Fisica | AT26: Ativo | AU26: 102 | AV26: 10 | AW26: 1 | AX26: 45847 | AY26: QUA/ | AZ26: 46022 | BA26: 0 | BB26: 0 | BC26: 0 | BD26: 700 | BE26: 70 | BF26: 9 | BG26: 45536 | BH26: DOM/ | BI26: 46026 | BJ26: 0 | BK26: 0 | BL26: 0 | BM26: 0 | BN26: 0 | BO26: 0 | BP26: 177.9 | BQ26: 830.2 | BR26: 0 | BS26: 0 | BT26: 0 | BU26: 0 | BV26: 1005.59 | BW26: 1005.59 | BX26: 0 | BY26: 0 | BZ26: 0 | CA26: 0 | CB26: 642.25 | CC26: Rota
A27: 345 | B27: 2 | C27: 78 | D27: 34.437.443/0001-66 | F27: BAR MANUEL MARCO | G27: MANOEL EDSON SILVA | H27: R RIOS SN | J27: CENTRO | K27: MARCO | L27: CE | M27: 62.560-000 | N27: 08 89809-2367 | O27: BAR/BARZINHO | P27: 0 | R27: 6 | S27: 42 | V27: 0 | W27: 0 | X27: 0 | Y27: 0 | Z27: 0 | AA27: 0 | AB27: 0 | AC27: 0 | AD27: Nao | AE27: Nao | AF27: 45518 | AG27: 46017 | AH27: 1052.8 | AI27: 1719 | AJ27: 12633.66 | AK27: 0 | AL27: 0 | AM27: 0 | AQ27: N | AS27: Juridica | AT27: Ativo | AU27: 102 | AV27: 10 | AW27: 1 | AX27: 45847 | AY27: QUA/ | AZ27: 46022 | BA27: 0 | BB27: 0 | BC27: 0 | BD27: 700 | BE27: 70 | BF27: 9 | BG27: 45536 | BH27: DOM/ | BI27: 46026 | BJ27: 0 | BK27: 0 | BL27: 0 | BM27: 0 | BN27: 0 | BO27: 0 | BP27: 3352.15 | BQ27: 3352.15 | BR27: 0 | BS27: 0 | BT27: 0 | BU27: 0 | BV27: 4129.68 | BW27: 4129.68 | BX27: 0 | BY27: 0 | BZ27: 0 | CA27: 0 | CB27: 5083.39 | CC27: Rota
A28: 345 | B28: 2 | C28: 79 | D28: 633.695.833-72 | F28: DEP DO JUNIOR MARCO | G28: ANTONIO FLAVIO DOS SANTOS | H28: RUA 22 DE NOVEMBRO 10 | J28: CENTRO | K28: MARCO | L28: CE | M28: 62.560-000 | N28: 08 89702-1221 | O28: DEPOSITO DE BEBIDAS | P28: 0 | R28: 6 | S28: 42 | V28: 0 | W28: 0 | X28: 0 | Y28: 0 | Z28: 0 | AA28: 0 | AB28: 0 | AC28: 0 | AD28: Nao | AE28: Nao | AF28: 45518 | AG28: 46014 | AH28: 5239.62 | AI28: 13046.41 | AJ28: 68115.12 | AK28: 0 | AL28: 0 | AM28: 0 | AQ28: N | AS28: Fisica | AT28: Ativo | AU28: 501 | AV28: 10 | AW28: 1 | AX28: 45856 | AY28: SEX/ | AZ28: 46024 | BA28: 0 | BB28: 0 | BC28: 0 | BD28: 700 | BE28: 70 | BF28: 9 | BG28: 45536 | BH28: DOM/ | BI28: 46026 | BJ28: 0 | BK28: 0 | BL28: 0 | BM28: 0 | BN28: 0 | BO28: 0 | BP28: 31077.22 | BQ28: 31077.22 | BR28: 0 | BS28: 0 | BT28: 0 | BU28: 0 | BV28: 22275.7 | BW28: 22275.7 | BX28: 0 | BY28: 0 | BZ28: 0 | CA28: 0 | CB28: 21111.22 | CC28: SUB
A29: 345 | B29: 2 | C29: 80 | D29: 010.374.023-67 | F29: CONV POSTO ROCHA | G29: ANDRE GUSTAVO OLIVEIRA ROCHA | H29: RUA BOM JESUS 10 | J29: TRIANGULO DO MARCO | K29: MARCO | L29: CE | M29: 62.560-000 | N29: 08 59970-6842 | O29: LOJA DE CONVENIENCIA | P29: 0 | R29: 6 | S29: 40 | V29: 0 | W29: 0 | X29: 0 | Y29: 0 | Z29: 0 | AA29: 0 | AB29: 0 | AC29: 0 | AD29: Nao | AE29: Nao | AF29: 45518 | AG29: 46017 | AH29: 695.48 | AI29: 881.68 | AJ29: 8345.84 | AK29: 0 | AL29: 0 | AM29: 0 | AQ29: N | AS29: Fisica | AT29: Ativo | AU29: 102 | AV29: 10 | AW29: 1 | AX29: 45903 | AY29: QUA/ | AZ29: 46022 | BA29: 0 | BB29: 0 | BC29: 0 | BD29: 700 | BE29: 70 | BF29: 9 | BG29: 45536 | BH29: DOM/ | BI29: 46026 | BJ29: 0 | BK29: 0 | BL29: 0 | BM29: 0 | BN29: 0 | BO29: 0 | BP29: 2508.34 | BQ29: 2508.34 | BR29: 0 | BS29: 0 | BT29: 0 | BU29: 0 | BV29: 2979.02 | BW29: 2979.02 | BX29: 0 | BY29: 0 | BZ29: 0 | CA29: 0 | CB29: 2248.15 | CC29: Lj. Conveniencia
A30: 345 | B30: 2 | C30: 81 | D30: 011.272.653-42 | F30: DEP DO MARCELO MARC | G30: MARCELO SILVA MOURA | H30: RUA MANOEL CLOVES RIOS 804 | J30: ALEMAES | K30: MARCO | L30: CE | M30: 62.560-000 | N30: 08 89724-0449 | O30: DEPOSITO DE BEBIDAS | P30: 0 | R30: 6 | S30: 41 | V30: 0 | W30: 0 | X30: 0 | Y30: 0 | Z30: 0 | AA30: 0 | AB30: 0 | AC30: 0 | AD30: Nao | AE30: Nao | AF30: 45518 | AG30: 46013 | AH30: 1642.81 | AI30: 1991.2 | AJ30: 4928.43 | AK30: 0 | AL30: 0 | AM30: 0 | AQ30: N | AS30: Fisica | AT30: Ativo | AU30: 102 | AV30: 10 | AW30: 1 | AX30: 45850 | AY30: SAB/ | AZ30: 46025 | BA30: 0 | BB30: 0 | BC30: 0 | BD30: 700 | BE30: 70 | BF30: 9 | BG30: 45536 | BH30: DOM/ | BI30: 46026 | BJ30: 0 | BK30: 0 | BL30: 0 | BM30: 0 | BN30: 0 | BO30: 0 | BP30: 0 | BQ30: 0 | BR30: 0 | BS30: 0 | BT30: 0 | BU30: 0 | BV30: 4928.43 | BW30: 4928.43 | BX30: 0 | BY30: 0 | BZ30: 0 | CA30: 0 | CB30: 0 | CC30: SUB
A31: 345 | B31: 2 | C31: 82 | D31: 069.895.533-16 | F31: MERC JP | G31: MARIA KAINARA VASCONCELOS | H31: R TRIANGULO DO MARCO 10 | J31: TRIANGULO DO MARCO | K31: MARCO | L31: CE | M31: 62.560-000 | N31: 88 89909-2507 | O31: ARMAZEM/MERCEARIA | P31: 0 | R31: 3 | S31: 89 | V31: 4328 | W31: 0 | X31: 4328 | Y31: 0 | Z31: 0 | AA31: 0 | AB31: 0 | AC31: 0 | AD31: Nao | AE31: Nao | AF31: 45518 | AG31: 46018 | AH31: 2020.53 | AI31: 4186.29 | AJ31: 18184.85 | AK31: 0 | AL31: 0 | AM31: 0 | AQ31: N | AS31: Fisica | AT31: Ativo | AU31: 102 | AV31: 10 | AW31: 1 | AX31: 45995 | AY31: QUI/ | AZ31: 46023 | BA31: 0 | BB31: 0 | BC31: 0 | BD31: 700 | BE31: 70 | BF31: 9 | BG31: 45536 | BH31: DOM/ | BI31: 46026 | BJ31: 0 | BK31: 0 | BL31: 0 | BM31: 0 | BN31: 0 | BO31: 0 | BP31: 10316.65 | BQ31: 10316.65 | BR31: 0 | BS31: 0 | BT31: 0 | BU31: 0 | BV31: 6939.2 | BW31: 6939.2 | BX31: 0 | BY31: 0 | BZ31: 0 | CA31: 0 | CB31: 7870.2 | CC31: TRAD
A32: 345 | B32: 2 | C32: 83 | D32: 725.858.113-87 | F32: BAIAO DE DOIS | G32: FRANCISCO EDSON MENEZES | H32: R RUA GOVERNADOR CESAR CALS SN | J32: CENTRO | K32: MARCO | L32: CE | M32: 62.560-000 | N32: 88 99914-3539 | O32: REST./PIZZARIA/CHURR | P32: 0 | R32: 3 | S32: 83 | V32: 1000 | W32: 952.99 | X32: 47.01 | Y32: 0 | Z32: 0 | AA32: 9 | AB32: 3 | AC32: 0 | AD32: Nao | AE32: Nao | AF32: 45518 | AG32: 46018 | AH32: 317.62 | AI32: 762.46 | AJ32: 1588.12 | AK32: 762.46 | AL32: 190.53 | AM32: 0 | AQ32: N | AS32: Fisica | AT32: Ativo | AU32: 102 | AV32: 10 | AW32: 1 | AX32: 45973 | AY32: QUA/ | AZ32: 46022 | BA32: 0 | BB32: 0 | BC32: 0 | BD32: 999 | BE32: 99 | BF32: 9 | BJ32: 0 | BK32: 0 | BL32: 0 | BM32: 0 | BN32: 0 | BO32: 0 | BP32: 418.15 | BQ32: 418.15 | BR32: 0 | BS32: 7.61 | BT32: 7.61 | BU32: 1169.97 | BV32: 0 | BW32: 1169.97 | BX32: 190.53 | BY32: 16.29 | BZ32: 0 | CA32: 0 | CB32: 139.38 | CC32: Rota
A33: 345 | B33: 2 | C33: 89 | D33: 070.759.943-10 | F33: MERC SAO GERALDO LA | G33: CANDIDA EDUARDA FREITAS DA SILVA | H33: R PV LAGOA DE SANTA ROSA 10 | J33: LAGOA DE SANTA ROSA | K33: MARCO | L33: CE | M33: 62.560-000 | N33: 88 89746-5132 | O33: ARMAZEM/MERCEARIA | P33: 0 | R33: 3 | S33: 89 | V33: 0 | W33: 0 | X33: 0 | Y33: 0 | Z33: 0 | AA33: 0 | AB33: 0 | AC33: 0 | AD33: Nao | AE33: Nao | AF33: 45518 | AG33: 46018 | AH33: 1403.85 | AI33: 2005.5 | AJ33: 2807.7 | AK33: 0 | AL33: 0 | AM33: 0 | AQ33: N | AS33: Fisica | AT33: Ativo | AU33: 102 | AV33: 10 | AW33: 1 | AX33: 45995 | AY33: QUI/ | AZ33: 46023 | BA33: 0 | BB33: 0 | BC33: 0 | BD33: 700 | BE33: 70 | BF33: 9 | BG33: 45536 | BH33: DOM/ | BI33: 46026 | BJ33: 0 | BK33: 0 | BL33: 0 | BM33: 0 | BN33: 0 | BO33: 0 | BP33: 0 | BQ33: 0 | BR33: 0 | BS33: 0 | BT33: 0 | BU33: 0 | BV33: 2807.7 | BW33: 2807.7 | BX33: 0 | BY33: 0 | BZ33: 0 | CA33: 0 | CB33: 0 | CC33: TRAD
A34: 345 | B34: 2 | C34: 96 | D34: 616.145.133-68 | F34: DEP SAO ROQUE MARCO | G34: ALEX DOS SANTOS | H34: R GOV CESAR CARLS SN | J34: CENTRO | K34: MARCO | L34: CE | M34: 62.560-000 | N34: 08 89840-2108 | O34: DEPOSITO DE BEBIDAS | P34: 0 | R34: 6 | S34: 40 | V34: 0 | W34: 0 | X34: 0 | Y34: 0 | Z34: 0 | AA34: 0 | AB34: 0 | AC34: 0 | AD34: Nao | AE34: Nao | AF34: 45518 | AG34: 46014 | AH34: 909.74 | AI34: 2290.4 | AJ34: 5458.45 | AK34: 0 | AL34: 0 | AM34: 0 | AQ34: N | AS34: Fisica | AT34: Ativo | AU34: 102 | AV34: 10 | AW34: 1 | AX34: 45810 | AY34: SEG/ | AZ34: 46027 | BA34: 0 | BB34: 0 | BC34: 0 | BD34: 700 | BE34: 70 | BF34: 9 | BG34: 45536 | BH34: DOM/ | BI34: 46026 | BJ34: 0 | BK34: 0 | BL34: 0 | BM34: 0 | BN34: 0 | BO34: 0 | BP34: 1982.05 | BQ34: 1982.05 | BR34: 0 | BS34: 0 | BT34: 0 | BU34: 0 | BV34: 2883.4 | BW34: 2883.4 | BX34: 0 | BY34: 0 | BZ34: 0 | CA34: 0 | CB34: 1431.35 | CC34: SUB
A35: 345 | B35: 2 | C35: 97 | D35: 014.531.423-55 | F35: DEPOSITO O PINTO | G35: PAULO ALEX DA COSTA DUARTE | H35: R PADRE APOLIANO SN | J35: CENTRO | K35: MARCO | L35: CE | M35: 62.560-000 | N35: 88 89652-1818 | O35: REST./PIZZARIA/CHURR | P35: 0 | R35: 3 | S35: 85 | V35: 2262 | W35: 0 | X35: 2262 | Y35: 0 | Z35: 0 | AA35: 0 | AB35: 0 | AC35: 0 | AD35: Nao | AE35: Nao | AF35: 45518 | AG35: 46021 | AH35: 2008.85 | AI35: 4834.96 | AJ35: 16070.83 | AK35: 0 | AL35: 0 | AM35: 0 | AQ35: N | AS35: Fisica | AT35: Ativo | AU35: 102 | AV35: 10 | AW35: 1 | AX35: 45810 | AY35: SEG/ | AZ35: 46027 | BA35: 0 | BB35: 0 | BC35: 0 | BD35: 700 | BE35: 70 | BF35: 9 | BG35: 45536 | BH35: DOM/ | BI35: 46026 | BJ35: 0 | BK35: 0 | BL35: 0 | BM35: 0 | BN35: 0 | BO35: 0 | BP35: 2511.91 | BQ35: 2511.91 | BR35: 0 | BS35: 0 | BT35: 0 | BU35: 0 | BV35: 9252.63 | BW35: 9252.63 | BX35: 0 | BY35: 0 | BZ35: 0 | CA35: 0 | CB35: 3655.87 | CC35: SUB
A36: 345 | B36: 2 | C36: 102 | D36: 064.497.153-32 | F36: MERC VVN LAGOA DO C | G36: JOAO PAULO DE PAULO SOUSA | H36: R PV LAGOA DO CANEMA SN | I36: PROX AO MERCADINHO VVN | J36: LAGOA DO CANEMA | K36: ACARAU | L36: CE | M36: 62.580-000 | N36: 08 89695-7642 | O36: ARMAZEM/MERCEARIA | P36: 0 | R36: 6 | S36: 39 | V36: 0 | W36: 0 | X36: 0 | Y36: 0 | Z36: 0 | AA36: 0 | AB36: 0 | AC36: 0 | AD36: Nao | AE36: Nao | AF36: 45518 | AG36: 46004 | AH36: 249.48 | AI36: 296 | AJ36: 1247.4 | AK36: 0 | AL36: 0 | AM36: 0 | AQ36: N | AS36: Fisica | AT36: Ativo | AU36: 101 | AV36: 10 | AW36: 1 | AX36: 45534 | AY36: SEX/ | AZ36: 46024 | BA36: 0 | BB36: 0 | BC36: 0 | BD36: 700 | BE36: 70 | BF36: 9 | BG36: 45536 | BH36: DOM/ | BI36: 46026 | BJ36: 0 | BK36: 0 | BL36: 0 | BM36: 0 | BN36: 0 | BO36: 0 | BP36: 532.8 | BQ36: 532.8 | BR36: 0 | BS36: 0 | BT36: 0 | BU36: 0 | BV36: 236.8 | BW36: 236.8 | BX36: 0 | BY36: 0 | BZ36: 0 | CA36: 0 | CB36: 492.2 | CC36: AS 1-4
A37: 345 | B37: 2 | C37: 103 | D37: 38.251.332/0001-11 | F37: MERC SAO FRANCISCO | G37: F KEILO ALVES ME | H37: RUA BOSQUE DOS NAMORADOS 425 | J37: TRIANGULO DO MARCO | K37: MARCO | L37: CE | M37: 62.560-000 | N37: 08 89819-9470 | O37: ARMAZEM/MERCEARIA | P37: 0 | R37: 6 | S37: 44 | V37: 0 | W37: 0 | X37: 0 | Y37: 0 | Z37: 0 | AA37: 0 | AB37: 0 | AC37: 0 | AD37: Nao | AE37: Nao | AF37: 45518 | AG37: 46020 | AH37: 1556.84 | AI37: 3848.02 | AJ37: 17125.24 | AK37: 0 | AL37: 0 | AM37: 0 | AQ37: N | AS37: Juridica | AT37: Ativo | AU37: 501 | AV37: 10 | AW37: 1 | AX37: 45856 | AY37: SEX/ | AZ37: 46024 | BA37: 0 | BB37: 0 | BC37: 0 | BD37: 700 | BE37: 70 | BF37: 9 | BG37: 45536 | BH37: DOM/ | BI37: 46026 | BJ37: 0 | BK37: 0 | BL37: 0 | BM37: 0 | BN37: 0 | BO37: 0 | BP37: 5707.18 | BQ37: 5707.18 | BR37: 0 | BS37: 0 | BT37: 0 | BU37: 0 | BV37: 9383.44 | BW37: 9383.44 | BX37: 0 | BY37: 0 | BZ37: 0 | CA37: 0 | CB37: 3719.51 | CC37: TRAD
A38: 345 | B38: 2 | C38: 105 | D38: 268.408.038-05 | F38: LANCHONETE CHAPADAO | G38: CLEBER JOSE DE SOUZA | H38: R JOSE MARIA FARIAS SN | J38: ALEMAES | K38: MARCO | L38: CE | M38: 62.560-000 | N38: 08 89950-5408 | O38: LANCHONETE/PASTELARI | P38: 0 | R38: 6 | S38: 36 | V38: 0 | W38: 0 | X38: 0 | Y38: 0 | Z38: 0 | AA38: 0 | AB38: 0 | AC38: 0 | AD38: Nao | AE38: Nao | AF38: 45518 | AG38: 46009 | AH38: 710.38 | AI38: 1300 | AJ38: 4262.28 | AK38: 0 | AL38: 0 | AM38: 0 | AQ38: N | AS38: Fisica | AT38: Ativo | AU38: 102 | AV38: 10 | AW38: 1 | AX38: 45847 | AY38: QUA/ | AZ38: 46022 | BA38: 0 | BB38: 0 | BC38: 0 | BD38: 700 | BE38: 70 | BF38: 9 | BG38: 45536 | BH38: DOM/ | BI38: 46026 | BJ38: 0 | BK38: 0 | BL38: 0 | BM38: 0 | BN38: 0 | BO38: 0 | BP38: 1300 | BQ38: 1300 | BR38: 0 | BS38: 0 | BT38: 0 | BU38: 0 | BV38: 1318.48 | BW38: 1318.48 | BX38: 0 | BY38: 0 | BZ38: 0 | CA38: 0 | CB38: 1357.22 | CC38: Rota
A39: 345 | B39: 2 | C39: 108 | D39: 027.844.783-00 | F39: DEP WLR RACOES MARC | G39: JOSE CARVALHO ROCHA | H39: RUA PROJETADA 3 | J39: ALEMAES | K39: MARCO | L39: CE | M39: 62.560-000 | N39: 08 89694-7763 | O39: DEPOSITO DE BEBIDAS | P39: 0 | R39: 6 | S39: 42 | V39: 0 | W39: 0 | X39: 0 | Y39: 0 | Z39: 0 | AA39: 0 | AB39: 0 | AC39: 0 | AD39: Nao | AE39: Nao | AF39: 45518 | AG39: 46019 | AH39: 5590 | AI39: 11370.15 | AJ39: 89440.06 | AK39: 0 | AL39: 0 | AM39: 0 | AQ39: N | AS39: Fisica | AT39: Ativo | AU39: 501 | AV39: 10 | AW39: 1 | AX39: 45856 | AY39: SEX/ | AZ39: 46024 | BA39: 0 | BB39: 0 | BC39: 0 | BD39: 700 | BE39: 70 | BF39: 9 | BG39: 45536 | BH39: DOM/ | BI39: 46026 | BJ39: 0 | BK39: 0 | BL39: 0 | BM39: 0 | BN39: 0 | BO39: 0 | BP39: 31297.62 | BQ39: 31297.62 | BR39: 0 | BS39: 0 | BT39: 0 | BU39: 0 | BV39: 36835.74 | BW39: 36835.74 | BX39: 0 | BY39: 0 | BZ39: 0 | CA39: 0 | CB39: 25719.79 | CC39: SUB
A40: 345 | B40: 2 | C40: 109 | D40: 083.532.053-78 | F40: MERC DO JOELIO TRIA | G40: JOSE JOELIO MARINHO | H40: R DO POSTO ROCHA SN | J40: TRIANGULO DO MARCO | K40: MARCO | L40: CE | M40: 62.560-000 | N40: 08 88898-7889 | O40: ARMAZEM/MERCEARIA | P40: 0 | R40: 6 | S40: 42 | V40: 0 | W40: 0 | X40: 0 | Y40: 0 | Z40: 0 | AA40: 0 | AB40: 0 | AC40: 0 | AD40: Nao | AE40: Nao | AF40: 45518 | AG40: 46017 | AH40: 2626.08 | AI40: 3743.6 | AJ40: 34139.16 | AK40: 0 | AL40: 0 | AM40: 0 | AQ40: N | AS40: Fisica | AT40: Ativo | AU40: 102 | AV40: 10 | AW40: 1 | AX40: 45842 | AY40: SEX/ | AZ40: 46024 | BA40: 0 | BB40: 0 | BC40: 0 | BD40: 700 | BE40: 70 | BF40: 9 | BG40: 45536 | BH40: DOM/ | BI40: 46026 | BJ40: 0 | BK40: 0 | BL40: 0 | BM40: 0 | BN40: 0 | BO40: 0 | BP40: 14360 | BQ40: 14360 | BR40: 0 | BS40: 0 | BT40: 0 | BU40: 0 | BV40: 10593.72 | BW40: 10593.72 | BX40: 0 | BY40: 0 | BZ40: 0 | CA40: 0 | CB40: 9844.12 | CC40: TRAD
A41: 345 | B41: 2 | C41: 117 | D41: 906.919.033-87 | F41: MERC VASCONCELOS | G41: JOSE REGINALDO VASCONCELOS | H41: RUA RUA GOVERNADOR RAUL BARBOSA 1054 | J41: COQUEIRINHO | K41: MARCO | L41: CE | M41: 62.560-000 | N41: 08 89857-9070 | O41: ARMAZEM/MERCEARIA | P41: 0 | R41: 6 | S41: 41 | V41: 0 | W41: 0 | X41: 0 | Y41: 0 | Z41: 0 | AA41: 0 | AB41: 0 | AC41: 0 | AD41: Nao | AE41: Nao | AF41: 45518 | AG41: 46011 | AH41: 120.8 | AI41: 186 | AJ41: 483.21 | AK41: 0 | AL41: 0 | AM41: 0 | AQ41: N | AS41: Fisica | AT41: Ativo | AU41: 102 | AV41: 10 | AW41: 1 | AX41: 45848 | AY41: QUI/ | AZ41: 46023 | BA41: 0 | BB41: 0 | BC41: 0 | BD41: 700 | BE41: 70 | BF41: 9 | BG41: 45536 | BH41: DOM/ | BI41: 46026 | BJ41: 0 | BK41: 0 | BL41: 0 | BM41: 0 | BN41: 0 | BO41: 0 | BP41: 111.21 | BQ41: 111.21 | BR41: 0 | BS41: 0 | BT41: 0 | BU41: 0 | BV41: 186 | BW41: 186 | BX41: 0 | BY41: 0 | BZ41: 0 | CA41: 0 | CB41: 122.6 | CC41: TRAD
A42: 345 | B42: 2 | C42: 118 | D42: 070.572.763-70 | F42: MERC SAO MANOEL NETO | G42: MARIANA ANTONIA MARAIS FONTELES | H42: AVE PREF GUIDO OSTERNO 10 | J42: CENTRO | K42: MARCO | L42: CE | M42: 62.560-000 | N42: 08 89984-8688 | O42: ARMAZEM/MERCEARIA | P42: 0 | R42: 6 | S42: 41 | V42: 0 | W42: 0 | X42: 0 | Y42: 0 | Z42: 0 | AA42: 0 | AB42: 0 | AC42: 0 | AD42: Nao | AE42: Nao | AF42: 45518 | AG42: 46021 | AH42: 981.88 | AI42: 3512.09 | AJ42: 9818.81 | AK42: 0 | AL42: 0 | AM42: 0 | AQ42: N | AS42: Fisica | AT42: Ativo | AU42: 102 | AV42: 10 | AW42: 1 | AX42: 45847 | AY42: QUA/ | AZ42: 46022 | BA42: 0 | BB42: 0 | BC42: 0 | BD42: 700 | BE42: 70 | BF42: 9 | BG42: 45536 | BH42: DOM/ | BI42: 46026 | BJ42: 0 | BK42: 0 | BL42: 0 | BM42: 0 | BN42: 0 | BO42: 0 | BP42: 528.27 | BQ42: 528.27 | BR42: 0 | BS42: 0 | BT42: 0 | BU42: 0 | BV42: 1411.63 | BW42: 1411.63 | BX42: 0 | BY42: 0 | BZ42: 0 | CA42: 0 | CB42: 5090 | CC42: TRAD
A43: 345 | B43: 2 | C43: 124 | D43: 949.074.553-72 | F43: DEP DIOGO ACARAU | G43: DIOGO HENRIQUE CARNEIRO DE BARROS | H43: RUA AVENIDA NICODEMOS ARAUJO 874 | J43: PAULO VI | K43: ACARAU | L43: CE | M43: 62.580-000 | N43: 08 48147-0116 | O43: DEPOSITO DE BEBIDAS | P43: 0 | R43: 6 | S43: 40 | V43: 0 | W43: 0 | X43: 0 | Y43: 0 | Z43: 0 | AA43: 0 | AB43: 0 | AC43: 0 | AD43: Nao | AE43: Nao | AF43: 45518 | AG43: 46008 | AH43: 742.27 | AI43: 1366.4 | AJ43: 6680.48 | AK43: 0 | AL43: 0 | AM43: 0 | AQ43: N | AS43: Fisica | AT43: Ativo | AU43: 101 | AV43: 10 | AW43: 1 | AX43: 45874 | AY43: TER/ | AZ43: 46028 | BA43: 0 | BB43: 0 | BC43: 0 | BD43: 700 | BE43: 70 | BF43: 9 | BG43: 45536 | BH43: DOM/ | BI43: 46026 | BJ43: 0 | BK43: 0 | BL43: 0 | BM43: 0 | BN43: 0 | BO43: 0 | BP43: 2079.48 | BQ43: 2079.48 | BR43: 0 | BS43: 0 | BT43: 0 | BU43: 0 | BV43: 1954.9 | BW43: 1954.9 | BX43: 0 | BY43: 0 | BZ43: 0 | CA43: 0 | CB43: 2396.63 | CC43: SUB
A44: 345 | B44: 2 | C44: 132 | D44: 059.076.153-62 | F44: DEP O CHIQUINHO VIL | G44: EFIGENIA LOPES DA SILVA | H44: VL VILA GADO BRAVO SN | I44: SN | J44: VILA GADO BRAVO | K44: MARCO | L44: CE | M44: 62.560-000 | N44: 08 89845-8319 | O44: DEPOSITO DE BEBIDAS | P44: 0 | R44: 6 | S44: 40 | V44: 0 | W44: 0 | X44: 0 | Y44: 0 | Z44: 0 | AA44: 0 | AB44: 0 | AC44: 0 | AD44: Nao | AE44: Nao | AF44: 45518 | AG44: 46021 | AH44: 1900.78 | AI44: 2632.91 | AJ44: 5702.35 | AK44: 0 | AL44: 0 | AM44: 0 | AQ44: N | AS44: Fisica | AT44: Ativo | AU44: 102 | AV44: 10 | AW44: 1 | AX44: 45537 | AY44: SEG/ | AZ44: 46027 | BA44: 0 | BB44: 0 | BC44: 0 | BD44: 700 | BE44: 70 | BF44: 9 | BG44: 45536 | BH44: DOM/ | BI44: 46026 | BJ44: 0 | BK44: 0 | BL44: 0 | BM44: 0 | BN44: 0 | BO44: 0 | BP44: 2632.91 | BQ44: 2632.91 | BR44: 0 | BS44: 0 | BT44: 0 | BU44: 0 | BV44: 3069.44 | BW44: 3069.44 | BX44: 0 | BY44: 0 | BZ44: 0 | CA44: 0 | CB44: 1608.43 | CC44: SUB
A45: 345 | B45: 2 | C45: 135 | D45: 063.389.523-79 | F45: DEP DE BEBIDAS RIOS | G45: FELIPE RIOS SILVA | H45: R PADRE APOLIANO SN | J45: ALEMAES | K45: MARCO | L45: CE | M45: 62.560-000 | N45: 08 89605-3644 | O45: DEPOSITO DE BEBIDAS | P45: 0 | R45: 6 | S45: 41 | V45: 0 | W45: 0 | X45: 0 | Y45: 0 | Z45: 0 | AA45: 0 | AB45: 0 | AC45: 0 | AD45: Nao | AE45: Nao | AF45: 45518 | AG45: 46020 | AH45: 1467.61 | AI45: 4569.53 | AJ45: 17611.43 | AK45: 0 | AL45: 0 | AM45: 0 | AQ45: N | AS45: Fisica | AT45: Ativo | AU45: 501 | AV45: 10 | AW45: 1 | AX45: 45856 | AY45: SEX/ | AZ45: 46024 | BA45: 0 | BB45: 0 | BC45: 0 | BD45: 700 | BE45: 70 | BF45: 9 | BG45: 45536 | BH45: DOM/ | BI45: 46026 | BJ45: 0 | BK45: 0 | BL45: 0 | BM45: 0 | BN45: 0 | BO45: 0 | BP45: 5384.38 | BQ45: 5384.38 | BR45: 0 | BS45: 0 | BT45: 0 | BU45: 0 | BV45: 8108.08 | BW45: 8108.08 | BX45: 0 | BY45: 0 | BZ45: 0 | CA45: 0 | CB45: 5129.29 | CC45: SUB
A46: 345 | B46: 2 | C46: 147 | D46: 074.635.363-43 | F46: MERC WELLINGTON | G46: WERIK ROCHA FILHO | H46: R R DEPUTADO MANOEL RODRIGUES SN | I46: SN | J46: CENTRO | K46: MARCO | L46: CE | M46: 62.560-000 | N46: 08 89637-0123 | O46: ARMAZEM/MERCEARIA | P46: 0 | R46: 6 | S46: 40 | V46: 0 | W46: 0 | X46: 0 | Y46: 0 | Z46: 0 | AA46: 0 | AB46: 0 | AC46: 0 | AD46: Nao | AE46: Nao | AF46: 45518 | AG46: 46009 | AH46: 2175.95 | AI46: 2759.7 | AJ46: 6527.86 | AK46: 0 | AL46: 0 | AM46: 0 | AQ46: N | AS46: Fisica | AT46: Ativo | AU46: 102 | AV46: 10 | AW46: 1 | AX46: 45854 | AY46: QUA/ | AZ46: 46022 | BA46: 0 | BB46: 0 | BC46: 0 | BD46: 700 | BE46: 70 | BF46: 9 | BG46: 45536 | BH46: DOM/ | BI46: 46026 | BJ46: 0 | BK46: 0 | BL46: 0 | BM46: 0 | BN46: 0 | BO46: 0 | BP46: 2107.78 | BQ46: 2107.78 | BR46: 0 | BS46: 0 | BT46: 0 | BU46: 0 | BV46: 1660.38 | BW46: 1660.38 | BX46: 0 | BY46: 0 | BZ46: 0 | CA46: 0 | CB46: 2541.87 | CC46: TRAD
A47: 345 | B47: 2 | C47: 148 | D47: 099.486.313-66 | F47: DEP DO EDUARDO MARC | G47: SAMUEL ARAUJO DOS SANTOS JUNIOR | H47: RUA RUA GOVER CESAR CALS 423 | I47: AVENIDA | J47: CENTRO | K47: MARCO | L47: CE | M47: 62.560-000 | N47: 08 89961-5460 | O47: DEPOSITO DE BEBIDAS | P47: 0 | R47: 6 | S47: 42 | V47: 0 | W47: 0 | X47: 0 | Y47: 0 | Z47: 0 | AA47: 0 | AB47: 0 | AC47: 0 | AD47: Nao | AE47: Nao | AF47: 45518 | AG47: 46019 | AH47: 4369.65 | AI47: 14506.68 | AJ47: 61175.23 | AK47: 0 | AL47: 0 | AM47: 0 | AQ47: N | AS47: Fisica | AT47: Ativo | AU47: 501 | AV47: 10 | AW47: 1 | AX47: 45856 | AY47: SEX/ | AZ47: 46024 | BA47: 0 | BB47: 0 | BC47: 0 | BD47: 700 | BE47: 70 | BF47: 9 | BG47: 45536 | BH47: DOM/ | BI47: 46026 | BJ47: 0 | BK47: 0 | BL47: 0 | BM47: 0 | BN47: 0 | BO47: 0 | BP47: 18767.13 | BQ47: 18767.13 | BR47: 0 | BS47: 0 | BT47: 0 | BU47: 0 | BV47: 29037.65 | BW47: 29037.65 | BX47: 0 | BY47: 0 | BZ47: 0 | CA47: 0 | CB47: 16120.59 | CC47: SUB
A48: 345 | B48: 2 | C48: 150 | D48: 035.073.653-75 | F48: COMERCIO DO SERGIO | G48: FRANCISCO SERGIO DUTRA | H48: VIL TRIANGULO DO MARCO 132 | J48: TRIANGULO DO MARCO | K48: MARCO | L48: CE | M48: 62.560-000 | N48: 08 89808-5471 | O48: ARMAZEM/MERCEARIA | P48: 0 | R48: 6 | S48: 39 | V48: 0 | W48: 0 | X48: 0 | Y48: 0 | Z48: 0 | AA48: 0 | AB48: 0 | AC48: 0 | AD48: Nao | AE48: Nao | AF48: 45518 | AG48: 46013 | AH48: 1165.39 | AI48: 1808.42 | AJ48: 5826.99 | AK48: 0 | AL48: 0 | AM48: 0 | AQ48: N | AS48: Fisica | AT48: Ativo | AU48: 102 | AV48: 10 | AW48: 1 | AX48: 45815 | AY48: SAB/ | AZ48: 46025 | BA48: 0 | BB48: 0 | BC48: 0 | BD48: 700 | BE48: 70 | BF48: 9 | BG48: 45536 | BH48: DOM/ | BI48: 46026 | BJ48: 0 | BK48: 0 | BL48: 0 | BM48: 0 | BN48: 0 | BO48: 0 | BP48: 1808.42 | BQ48: 1808.42 | BR48: 0 | BS48: 0 | BT48: 0 | BU48: 0 | BV48: 2943.89 | BW48: 2943.89 | BX48: 0 | BY48: 0 | BZ48: 0 | CA48: 0 | CB48: 1664.49 | CC48: TRAD
A49: 345 | B49: 2 | C49: 152 | D49: 48.527.217/0001-80 | F49: DEP DO OLAVO MARCO | G49: JOSE OLAVO TEOFILO | H49: RUA RUA RIOS 222 | I49: AO LADO DA MERCEARIA GIFONE | J49: CENTRO | K49: MARCO | L49: CE | M49: 62.560-000 | N49: 08 89762-5033 | O49: DEPOSITO DE BEBIDAS | P49: 0 | R49: 6 | S49: 45 | V49: 0 | W49: 0 | X49: 0 | Y49: 0 | Z49: 0 | AA49: 0 | AB49: 0 | AC49: 0 | AD49: Nao | AE49: Nao | AF49: 45518 | AG49: 46021 | AH49: 1436.54 | AI49: 2344.6 | AJ49: 14365.41 | AK49: 0 | AL49: 0 | AM49: 0 | AQ49: N | AS49: Juridica | AT49: Ativo | AU49: 102 | AV49: 10 | AW49: 1 | AX49: 45810 | AY49: SEG/ | AZ49: 46027 | BA49: 0 | BB49: 0 | BC49: 0 | BD49: 700 | BE49: 70 | BF49: 9 | BG49: 45536 | BH49: DOM/ | BI49: 46026 | BJ49: 0 | BK49: 0 | BL49: 0 | BM49: 0 | BN49: 0 | BO49: 0 | BP49: 3693.02 | BQ49: 3693.02 | BR49: 0 | BS49: 0 | BT49: 0 | BU49: 0 | BV49: 6618.24 | BW49: 6618.24 | BX49: 0 | BY49: 0 | BZ49: 0 | CA49: 0 | CB49: 3764.14 | CC49: SUB
A50: 345 | B50: 2 | C50: 154 | D50: 080.735.793-67 | F50: CHURRASCARIA BELO SA | G50: CAIO JARBAS DO NASCIMENTO | H50: AV AV PREFEITO GUIDO OSTERNO SN | J50: CENTRO | K50: MARCO | L50: CE | M50: 62.560-000 | N50: 08 59841-6972 | O50: REST./PIZZARIA/CHURR | P50: 0 | R50: 6 | S50: 36 | V50: 0 | W50: 0 | X50: 0 | Y50: 0 | Z50: 0 | AA50: 0 | AB50: 0 | AC50: 0 | AD50: Nao | AE50: Nao | AF50: 45518 | AG50: 46009 | AH50: 1332.62 | AI50: 2414.82 | AJ50: 5330.49 | AK50: 0 | AL50: 0 | AM50: 0 | AQ50: N | AS50: Fisica | AT50: Ativo | AU50: 102 | AV50: 10 | AW50: 1 | AX50: 45847 | AY50: QUA/ | AZ50: 46022 | BA50: 0 | BB50: 0 | BC50: 0 | BD50: 700 | BE50: 70 | BF50: 9 | BG50: 45536 | BH50: DOM/ | BI50: 46026 | BJ50: 0 | BK50: 0 | BL50: 0 | BM50: 0 | BN50: 0 | BO50: 0 | BP50: 2316.38 | BQ50: 2316.38 | BR50: 0 | BS50: 0 | BT50: 0 | BU50: 0 | BV50: 42.63 | BW50: 42.63 | BX50: 0 | BY50: 0 | BZ50: 0 | CA50: 0 | CB50: 2209.07 | CC50: Rota
A51: 345 | B51: 2 | C51: 156 | D51: 012.050.003-56 | F51: BAR E MERC EVELINE | G51: MARIA EVILENE BEZERRA DIAS | H51: VIL TRIANGULO DO MARCO 10000 | I51: VIZINHO AO MARINO SOEIRA | J51: TRIANGULO DO MARCO | K51: MARCO | L51: CE | M51: 62.560-000 | N51: 08 59771-8488 | O51: BAR/BARZINHO | P51: 0 | R51: 6 | S51: 38 | V51: 0 | W51: 0 | X51: 0 | Y51: 0 | Z51: 0 | AA51: 0 | AB51: 0 | AC51: 0 | AD51: Nao | AE51: Nao | AF51: 45518 | AG51: 46020 | AH51: 1318.87 | AI51: 1661.8 | AJ51: 17145.32 | AK51: 0 | AL51: 0 | AM51: 0 | AQ51: N | AS51: Fisica | AT51: Ativo | AU51: 102 | AV51: 10 | AW51: 1 | AX51: 45815 | AY51: SAB/ | AZ51: 46025 | BA51: 0 | BB51: 0 | BC51: 0 | BD51: 700 | BE51: 70 | BF51: 9 | BG51: 45536 | BH51: DOM/ | BI51: 46026 | BJ51: 0 | BK51: 0 | BL51: 0 | BM51: 0 | BN51: 0 | BO51: 0 | BP51: 4710.41 | BQ51: 4710.41 | BR51: 0 | BS51: 0 | BT51: 0 | BU51: 0 | BV51: 7309.66 | BW51: 7309.66 | BX51: 0 | BY51: 0 | BZ51: 0 | CA51: 0 | CB51: 4754.92 | CC51: Rota
A52: 345 | B52: 2 | C52: 163 | D52: 050.816.313-70 | F52: JR BEBIDAS TRIANGUL | G52: JAIR RONNYS ALVES | H52: VL TRIANGULO DO MARCO 1000 | I52: PERTO DA OFICINA DO ZE BI | J52: TRIANGULO DO MARCO | K52: MARCO | L52: CE | M52: 62.560-000 | N52: 88 89818-2074 | O52: DEPOSITO DE BEBIDAS | P52: 0 | R52: 3 | S52: 89 | V52: 1980 | W52: 0 | X52: 1980 | Y52: 0 | Z52: 0 | AA52: 0 | AB52: 0 | AC52: 0 | AD52: Nao | AE52: Nao | AF52: 45518 | AG52: 46018 | AH52: 1305.14 | AI52: 1805.14 | AJ52: 15661.69 | AK52: 0 | AL52: 0 | AM52: 0 | AQ52: N | AS52: Fisica | AT52: Ativo | AU52: 102 | AV52: 10 | AW52: 1 | AX52: 45995 | AY52: QUI/ | AZ52: 46023 | BA52: 0 | BB52: 0 | BC52: 0 | BD52: 700 | BE52: 70 | BF52: 9 | BG52: 45536 | BH52: DOM/ | BI52: 46026 | BJ52: 0 | BK52: 0 | BL52: 0 | BM52: 0 | BN52: 0 | BO52: 0 | BP52: 5811.57 | BQ52: 5811.57 | BR52: 0 | BS52: 0 | BT52: 0 | BU52: 0 | BV52: 5472.78 | BW52: 5472.78 | BX52: 0 | BY52: 0 | BZ52: 0 | CA52: 0 | CB52: 4265.99 | CC52: SUB
A53: 345 | B53: 2 | C53: 165 | D53: 906.881.473-72 | F53: MERCEARIA O FROTAO | G53: JOSE FROTA BASILIO | H53: Rua RUA DEPUTADO MANOEL RODRIGUES 900 | J53: CENTRO | K53: MARCO | L53: CE | M53: 62.560-000 | N53: 08 89741-3259 | O53: ARMAZEM/MERCEARIA | P53: 0 | R53: 6 | S53: 40 | V53: 0 | W53: 0 | X53: 0 | Y53: 0 | Z53: 0 | AA53: 0 | AB53: 0 | AC53: 0 | AD53: Nao | AE53: Nao | AF53: 45518 | AG53: 46009 | AH53: 279.99 | AI53: 415.22 | AJ53: 2799.99 | AK53: 0 | AL53: 0 | AM53: 0 | AQ53: N | AS53: Fisica | AT53: Ativo | AU53: 102 | AV53: 10 | AW53: 1 | AX53: 45847 | AY53: QUA/ | AZ53: 46022 | BA53: 0 | BB53: 0 | BC53: 0 | BD53: 700 | BE53: 70 | BF53: 9 | BG53: 45536 | BH53: DOM/ | BI53: 46026 | BJ53: 0 | BK53: 0 | BL53: 0 | BM53: 0 | BN53: 0 | BO53: 0 | BP53: 1060.85 | BQ53: 1060.85 | BR53: 0 | BS53: 0 | BT53: 0 | BU53: 0 | BV53: 909.08 | BW53: 909.08 | BX53: 0 | BY53: 0 | BZ53: 0 | CA53: 0 | CB53: 742.78 | CC53: TRAD
A54: 345 | B54: 2 | C54: 167 | D54: 011.238.603-27 | F54: RESTAURANTE BOM GOST | G54: MARIA GLEYDIANE LEITE MESSIAS | H54: VIL TRIANGULO DO MARCO 1000 | I54: PROXIMO AO POSTO DE MARIA | J54: TRIANGULO DO MARCO | K54: MARCO | L54: CE | M54: 62.560-000 | N54: 08 89671-6120 | O54: REST./PIZZARIA/CHURR | P54: 0 | R54: 6 | S54: 36 | V54: 0 | W54: 0 | X54: 0 | Y54: 0 | Z54: 0 | AA54: 0 | AB54: 0 | AC54: 0 | AD54: Nao | AE54: Nao | AF54: 45518 | AG54: 46011 | AH54: 206.8 | AI54: 279.04 | AJ54: 1447.66 | AK54: 0 | AL54: 0 | AM54: 0 | AQ54: N | AS54: Fisica | AT54: Ativo | AU54: 102 | AV54: 10 | AW54: 1 | AX54: 45814 | AY54: SEX/ | AZ54: 46024 | BA54: 0 | BB54: 0 | BC54: 0 | BD54: 700 | BE54: 70 | BF54: 9 | BG54: 45536 | BH54: DOM/ | BI54: 46026 | BJ54: 0 | BK54: 0 | BL54: 0 | BM54: 0 | BN54: 0 | BO54: 0 | BP54: 628.38 | BQ54: 628.38 | BR54: 0 | BS54: 0 | BT54: 0 | BU54: 0 | BV54: 201.84 | BW54: 201.84 | BX54: 0 | BY54: 0 | BZ54: 0 | CA54: 0 | CB54: 705.93 | CC54: Rota
A55: 345 | B55: 2 | C55: 170 | D55: 050.192.923-11 | F55: PIZZARIA DO GERALDO | G55: MARIA GLAUCIA DOS SANTOS | H55: VIL Santa Rosa 1000 | J55: SANTA ROSA | K55: MARCO | L55: CE | M55: 62.560-000 | N55: 08 89845-1575 | O55: REST./PIZZARIA/CHURR | P55: 0 | R55: 6 | S55: 36 | V55: 0 | W55: 0 | X55: 0 | Y55: 0 | Z55: 0 | AA55: 0 | AB55: 0 | AC55: 0 | AD55: Nao | AE55: Nao | AF55: 45518 | AG55: 46021 | AH55: 907.47 | AI55: 1918.8 | AJ55: 11797.23 | AK55: 0 | AL55: 0 | AM55: 0 | AQ55: N | AS55: Fisica | AT55: Ativo | AU55: 102 | AV55: 10 | AW55: 1 | AX55: 45537 | AY55: SEG/ | AZ55: 46027 | BA55: 0 | BB55: 0 | BC55: 0 | BD55: 700 | BE55: 70 | BF55: 9 | BG55: 45536 | BH55: DOM/ | BI55: 46026 | BJ55: 0 | BK55: 0 | BL55: 0 | BM55: 0 | BN55: 0 | BO55: 0 | BP55: 3773.45 | BQ55: 3773.45 | BR55: 0 | BS55: 0 | BT55: 0 | BU55: 0 | BV55: 5343.52 | BW55: 5343.52 | BX55: 0 | BY55: 0 | BZ55: 0 | CA55: 0 | CB55: 3527.29 | CC55: Rota
A56: 345 | B56: 2 | C56: 176 | D56: 076.390.783-93 | F56: DISTRIBUIDORA RIOS | G56: ANTONIO EUDES FERREIRA | H56: RUA RUA ANTONIO MIRNEVINO VASCONCELOS 56 | J56: CENTRO | K56: MARCO | L56: CE | M56: 62.560-000 | N56: 08 89711-1007 | O56: DEPOSITO DE BEBIDAS | P56: 0 | R56: 6 | S56: 44 | V56: 0 | W56: 0 | X56: 0 | Y56: 0 | Z56: 0 | AA56: 0 | AB56: 0 | AC56: 0 | AD56: Nao | AE56: Nao | AF56: 45518 | AG56: 46020 | AH56: 26291.19 | AI56: 125888.43 | AJ56: 736153.53 | AK56: 0 | AL56: 0 | AM56: 0 | AQ56: N | AS56: Fisica | AT56: Ativo | AU56: 501 | AV56: 10 | AW56: 1 | AX56: 45856 | AY56: SEX/ | AZ56: 46024 | BA56: 0 | BB56: 0 | BC56: 0 | BD56: 700 | BE56: 70 | BF56: 9 | BG56: 45536 | BH56: DOM/ | BI56: 46026 | BJ56: 0 | BK56: 0 | BL56: 0 | BM56: 0 | BN56: 0 | BO56: 0 | BP56: 256778.03 | BQ56: 256778.03 | BR56: 0 | BS56: 0 | BT56: 0 | BU56: 0 | BV56: 414650.83 | BW56: 414650.83 | BX56: 0 | BY56: 0 | BZ56: 0 | CA56: 0 | CB56: 165679.69 | CC56: SUB
A57: 345 | B57: 2 | C57: 183 | D57: 49.460.383/0001-70 | F57: DEPOSITO DO LEORNE | G57: GUILESPE RIOS LEORNE | H57: R RUA PARSIFAL BARROSO SN | I57: PROXIMO A IGREJA MATRIX DEARCO | J57: SANTA ROSA | K57: MARCO | L57: CE | M57: 62.560-000 | N57: 08 89614-0865 | O57: DEPOSITO DE BEBIDAS | P57: 0 | R57: 6 | S57: 44 | V57: 0 | W57: 0 | X57: 0 | Y57: 0 | Z57: 0 | AA57: 0 | AB57: 0 | AC57: 0 | AD57: Nao | AE57: Nao | AF57: 45518 | AG57: 46006 | AH57: 1172.68 | AI57: 1655.6 | AJ57: 10554.18 | AK57: 0 | AL57: 0 | AM57: 0 | AQ57: N | AS57: Juridica | AT57: Ativo | AU57: 501 | AV57: 10 | AW57: 1 | AX57: 45856 | AY57: SEX/ | AZ57: 46024 | BA57: 0 | BB57: 0 | BC57: 0 | BD57: 700 | BE57: 70 | BF57: 9 | BG57: 45536 | BH57: DOM/ | BI57: 46026 | BJ57: 0 | BK57: 0 | BL57: 0 | BM57: 0 | BN57: 0 | BO57: 0 | BP57: 3060.84 | BQ57: 3060.84 | BR57: 0 | BS57: 0 | BT57: 0 | BU57: 0 | BV57: 4379.74 | BW57: 4379.74 | BX57: 0 | BY57: 0 | BZ57: 0 | CA57: 0 | CB57: 2993.08 | CC57: SUB
A58: 345 | B58: 2 | C58: 185 | D58: 026.829.133-00 | F58: ADEGA DO ARI | G58: ARI DHEIME JONE NASCIMENTO | H58: RUA ENTRADA ARANAU DO LADO DA ESCOLA1 | J58: ARANAU | K58: ACARAU | L58: CE | M58: 62.580-000 | N58: 08 88177-2773 | O58: DEPOSITO DE BEBIDAS | P58: 0 | R58: 6 | S58: 42 | V58: 0 | W58: 0 | X58: 0 | Y58: 0 | Z58: 0 | AA58: 0 | AB58: 0 | AC58: 0 | AD58: Nao | AE58: Nao | AF58: 45518 | AG58: 46015 | AH58: 2032.52 | AI58: 3841.45 | AJ58: 28455.36 | AK58: 0 | AL58: 1720.8 | AM58: 0 | AQ58: N | AS58: Fisica | AT58: Ativo | AU58: 100 | AV58: 10 | AW58: 1 | AX58: 45824 | AY58: SEG/ | AZ58: 46027 | BA58: 0 | BB58: 0 | BC58: 0 | BD58: 700 | BE58: 70 | BF58: 9 | BG58: 45536 | BH58: DOM/ | BI58: 46026 | BJ58: 0 | BK58: 0 | BL58: 0 | BM58: 0 | BN58: 0 | BO58: 0 | BP58: 10816.89 | BQ58: 10816.89 | BR58: 0 | BS58: 0 | BT58: 0 | BU58: 0 | BV58: 10693.99 | BW58: 10693.99 | BX58: 0 | BY58: 0 | BZ58: 0 | CA58: 0 | CB58: 8400.91 | CC58: SUB
A59: 345 | B59: 2 | C59: 186 | D59: 40.475.398/0001-37 | F59: SUPERMERCADO PAGUE M | G59: C E SUPERMERCADO LTDA | H59: RUA 07 DE SETEMBRO 347 | I59: PROX AO PRIMOS GRILL | J59: CENTRO | K59: CRUZ | L59: CE | M59: 62.595-000 | N59: 88 99783-4872 | O59: ARMAZEM/MERCEARIA | P59: 0 | R59: 6 | S59: 46 | V59: 0 | W59: 0 | X59: 0 | Y59: 0 | Z59: 0 | AA59: 0 | AB59: 0 | AC59: 0 | AD59: Nao | AE59: Nao | AF59: 45518 | AG59: 46020 | AH59: 3028.69 | AI59: 5046.5 | AJ59: 36344.38 | AK59: 0 | AL59: 0 | AM59: 0 | AQ59: N | AS59: Juridica | AT59: Ativo | AU59: 501 | AV59: 10 | AW59: 1 | AX59: 45854 | AY59: QUA/ | AZ59: 46022 | BA59: 0 | BB59: 0 | BC59: 0 | BD59: 700 | BE59: 70 | BF59: 9 | BG59: 45536 | BH59: DOM/ | BI59: 46026 | BJ59: 0 | BK59: 0 | BL59: 0 | BM59: 0 | BN59: 0 | BO59: 0 | BP59: 10431.34 | BQ59: 10431.34 | BR59: 0 | BS59: 0 | BT59: 0 | BU59: 0 | BV59: 8980.93 | BW59: 8980.93 | BX59: 0 | BY59: 0 | BZ59: 0 | CA59: 0 | CB59: 12321.41 | CC59: TRAD
A60: 345 | B60: 2 | C60: 187 | D60: 07.780.869/0001-45 | F60: PEDRO DUTRA BELA CR | G60: PEDRO ROGERIO MORAIS | H60: RUA HUMAITA 117 | J60: CENTRO | K60: BELA CRUZ | L60: CE | M60: 62.570-000 | N60: 08 89693-1600 | O60: DEPOSITO DE BEBIDAS | P60: 0 | R60: 6 | S60: 45 | V60: 0 | W60: 0 | X60: 0 | Y60: 0 | Z60: 0 | AA60: 0 | AB60: 0 | AC60: 0 | AD60: Nao | AE60: Nao | AF60: 45518 | AG60: 46020 | AH60: 5347.76 | AI60: 26267.21 | AJ60: 48129.91 | AK60: 0 | AL60: 0 | AM60: 0 | AQ60: N | AS60: Juridica | AT60: Ativo | AU60: 501 | AV60: 10 | AW60: 1 | AX60: 45856 | AY60: SEX/ | AZ60: 46024 | BA60: 0 | BB60: 0 | BC60: 0 | BD60: 700 | BE60: 70 | BF60: 9 | BG60: 45536 | BH60: DOM/ | BI60: 46026 | BJ60: 0 | BK60: 0 | BL60: 0 | BM60: 0 | BN60: 0 | BO60: 0 | BP60: 584.13 | BQ60: 584.13 | BR60: 0 | BS60: 0 | BT60: 0 | BU60: 0 | BV60: 41792.86 | BW60: 41792.86 | BX60: 0 | BY60: 0 | BZ60: 0 | CA60: 0 | CB60: 12329.84 | CC60: SUB
A61: 345 | B61: 2 | C61: 188 | D61: 16.435.559/0001-84 | F61: C E MERCANTIL CENT | G61: DEBORA VALQUIRIA DO NASCIMENTO ME | H61: RUA R EXPEDITO FARIAS 259 | J61: CENTRO | K61: ACARAU | L61: CE | M61: 62.580-000 | N61: 08 89767-7250 | O61: ARMAZEM/MERCEARIA | P61: 0 | R61: 6 | S61: 43 | V61: 0 | W61: 0 | X61: 0 | Y61: 0 | Z61: 0 | AA61: 0 | AB61: 0 | AC61: 0 | AD61: Nao | AE61: Nao | AF61: 45518 | AG61: 46003 | AH61: 283.64 | AI61: 335.28 | AJ61: 1134.59 | AK61: 0 | AL61: 0 | AM61: 0 | AQ61: N | AS61: Juridica | AT61: Ativo | AU61: 101 | AV61: 10 | AW61: 1 | AX61: 45967 | AY61: QUI/ | AZ61: 46023 | BA61: 0 | BB61: 0 | BC61: 0 | BD61: 700 | BE61: 70 | BF61: 9 | BG61: 45536 | BH61: DOM/ | BI61: 46026 | BJ61: 0 | BK61: 0 | BL61: 0 | BM61: 0 | BN61: 0 | BO61: 0 | BP61: 319.22 | BQ61: 319.22 | BR61: 0 | BS61: 0 | BT61: 0 | BU61: 0 | BV61: 214.13 | BW61: 214.13 | BX61: 0 | BY61: 0 | BZ61: 0 | CA61: 0 | CB61: 490.82 | CC61: TRAD
A62: 345 | B62: 2 | C62: 189 | D62: 728.076.363-49 | F62: BAR DA EUNICE CENTR | G62: EUNICE MATIAS DA SILVA MIRANDA | H62: R PREFEITO RAIMUNDO ROCHA SN | I62: PROX AO HOTEL RIVIERA | J62: CENTRO | K62: ACARAU | L62: CE | M62: 62.580-000 | N62: 88 99854-6725 | O62: BAR/BARZINHO | P62: 0 | R62: 6 | S62: 36 | V62: 0 | W62: 0 | X62: 0 | Y62: 0 | Z62: 0 | AA62: 0 | AB62: 0 | AC62: 0 | AD62: Nao | AE62: Nao | AF62: 45518 | AG62: 46015 | AH62: 580.66 | AI62: 1216.2 | AJ62: 6968.02 | AK62: 0 | AL62: 0 | AM62: 0 | AQ62: N | AS62: Fisica | AT62: Ativo | AU62: 101 | AV62: 10 | AW62: 1 | AX62: 45874 | AY62: TER/ | AZ62: 46028 | BA62: 0 | BB62: 0 | BC62: 0 | BD62: 700 | BE62: 70 | BF62: 9 | BG62: 45536 | BH62: DOM/ | BI62: 46026 | BJ62: 0 | BK62: 0 | BL62: 0 | BM62: 0 | BN62: 0 | BO62: 0 | BP62: 1605 | BQ62: 1605 | BR62: 0 | BS62: 0 | BT62: 0 | BU62: 0 | BV62: 1791.01 | BW62: 1791.01 | BX62: 0 | BY62: 0 | BZ62: 0 | CA62: 0 | CB62: 2622.41 | CC62: Rota
A63: 345 | B63: 2 | C63: 190 | D63: 600.774.373-06 | F63: RANCHO DOS LOPES GE | G63: ROBERTO DIONEI LOPES | H63: RUA RANCHO DO LOPES 10000 | I63: A 100 METROS DO PESQUE PAGUE | J63: GENIPAPEIRO | K63: CRUZ | L63: CE | M63: 62.595-000 | N63: 08 89709-5162 | O63: BAR/BARZINHO | P63: 0 | R63: 6 | S63: 37 | V63: 0 | W63: 0 | X63: 0 | Y63: 0 | Z63: 0 | AA63: 0 | AB63: 0 | AC63: 0 | AD63: Nao | AE63: Nao | AF63: 45518 | AG63: 46021 | AH63: 1212.48 | AI63: 2436.49 | AJ63: 13337.31 | AK63: 0 | AL63: 0 | AM63: 0 | AQ63: N | AS63: Fisica | AT63: Ativo | AU63: 105 | AV63: 10 | AW63: 1 | AX63: 45810 | AY63: SEG/ | AZ63: 46027 | BA63: 0 | BB63: 0 | BC63: 0 | BD63: 700 | BE63: 70 | BF63: 9 | BG63: 45536 | BH63: DOM/ | BI63: 46026 | BJ63: 0 | BK63: 0 | BL63: 0 | BM63: 0 | BN63: 0 | BO63: 0 | BP63: 3775.41 | BQ63: 3775.41 | BR63: 0 | BS63: 0 | BT63: 0 | BU63: 0 | BV63: 6046.49 | BW63: 6046.49 | BX63: 0 | BY63: 0 | BZ63: 0 | CA63: 0 | CB63: 3564.97 | CC63: Rota
A64: 345 | B64: 2 | C64: 192 | D64: 512.627.703-00 | F64: BAR O PANTANAL ACAR | G64: BERNADETE DO NASCIMENTO RODRIGUES | H64: RUA R JOSE MONTEIRO DE MELO 10000 | I64: S/N | J64: SAGUIM | K64: ACARAU | L64: CE | M64: 62.580-000 | N64: 88 99679-6291 | O64: BAR/BARZINHO | P64: 0 | R64: 6 | S64: 36 | V64: 0 | W64: 0 | X64: 0 | Y64: 0 | Z64: 0 | AA64: 0 | AB64: 0 | AC64: 0 | AD64: Nao | AE64: Nao | AF64: 45518 | AG64: 46017 | AH64: 330.19 | AI64: 441.92 | AJ64: 2971.79 | AK64: 0 | AL64: 0 | AM64: 0 | AQ64: N | AS64: Fisica | AT64: Ativo | AU64: 101 | AV64: 10 | AW64: 1 | AX64: 45854 | AY64: QUA/ | AZ64: 46022 | BA64: 0 | BB64: 0 | BC64: 0 | BD64: 700 | BE64: 70 | BF64: 9 | BG64: 45536 | BH64: DOM/ | BI64: 46026 | BJ64: 0 | BK64: 0 | BL64: 0 | BM64: 0 | BN64: 0 | BO64: 0 | BP64: 1130.76 | BQ64: 1130.76 | BR64: 0 | BS64: 0 | BT64: 0 | BU64: 0 | BV64: 1580.15 | BW64: 1580.15 | BX64: 0 | BY64: 0 | BZ64: 0 | CA64: 0 | CB64: 643.43 | CC64: Rota
A65: 345 | B65: 2 | C65: 193 | D65: 060.769.653-20 | F65: MERC PRECO BOM PORT | G65: FRANCISCO DEIJAIR FARIAS | H65: R PORTEIRAS SN | J65: PORTEIRAS | K65: ACARAU | L65: CE | M65: 62.580-000 | N65: 88 99796-3614 | O65: ARMAZEM/MERCEARIA | P65: 0 | R65: 6 | S65: 41 | V65: 0 | W65: 0 | X65: 0 | Y65: 0 | Z65: 0 | AA65: 0 | AB65: 0 | AC65: 0 | AD65: Nao | AE65: Nao | AF65: 45518 | AG65: 45999 | AH65: 286.5 | AI65: 286.5 | AJ65: 286.5 | AK65: 0 | AL65: 0 | AM65: 0 | AQ65: N | AS65: Fisica | AT65: Ativo | AU65: 100 | AV65: 10 | AW65: 1 | AX65: 45815 | AY65: SAB/ | AZ65: 46025 | BA65: 0 | BB65: 0 | BC65: 0 | BD65: 700 | BE65: 70 | BF65: 9 | BG65: 45536 | BH65: DOM/ | BI65: 46026 | BJ65: 0 | BK65: 0 | BL65: 0 | BM65: 0 | BN65: 0 | BO65: 0 | BP65: 0 | BQ65: 0 | BR65: 0 | BS65: 0 | BT65: 0 | BU65: 0 | BV65: 286.5 | BW65: 286.5 | BX65: 0 | BY65: 0 | BZ65: 0 | CA65: 0 | CB65: 48.76 | CC65: TRAD
A66: 345 | B66: 2 | C66: 194 | D66: 28.075.874/0001-27 | F66: MERCADINHO JB CENTR | G66: JAILMA LIMA LIBARINO | H66: RUA MANOEL SALES 380 | J66: CENTRO | K66: ACARAU | L66: CE | M66: 62.580-000 | N66: 88 99775-7298 | O66: ARMAZEM/MERCEARIA | P66: 0 | R66: 6 | S66: 43 | V66: 0 | W66: 0 | X66: 0 | Y66: 0 | Z66: 0 | AA66: 0 | AB66: 0 | AC66: 0 | AD66: Nao | AE66: Nao | AF66: 45518 | AG66: 46003 | AH66: 222.95 | AI66: 309.37 | AJ66: 1337.73 | AK66: 0 | AL66: 0 | AM66: 0 | AQ66: N | AS66: Juridica | AT66: Ativo | AU66: 101 | AV66: 10 | AW66: 1 | AX66: 45841 | AY66: QUI/ | AZ66: 46023 | BA66: 0 | BB66: 0 | BC66: 0 | BD66: 700 | BE66: 70 | BF66: 9 | BG66: 45536 | BH66: DOM/ | BI66: 46026 | BJ66: 0 | BK66: 0 | BL66: 0 | BM66: 0 | BN66: 0 | BO66: 0 | BP66: 452.6 | BQ66: 452.6 | BR66: 0 | BS66: 0 | BT66: 0 | BU66: 0 | BV66: 325.51 | BW66: 325.51 | BX66: 0 | BY66: 0 | BZ66: 0 | CA66: 0 | CB66: 553.68 | CC66: TRAD
A67: 345 | B67: 2 | C67: 197 | D67: 27.591.784/0001-26 | F67: ZE - ARMAZEM EXPRESS | G67: ACARAU CONVENIENCIA | H67: AV AV JOAO JAIME FERREIRA GOMES 517 | J67: CENTRO | K67: ACARAU | L67: CE | M67: 62.580-000 | N67: 85 99958-0826 | O67: LOJA DE CONVENIENCIA | P67: 0 | R67: 3 | S67: 86 | V67: 19000 | W67: 0 | X67: 19000 | Y67: 7 | Z67: 0 | AA67: 4 | AB67: 0 | AC67: 5 | AD67: Sim | AE67: Nao | AF67: 45518 | AG67: 45995 | AH67: 1365.83 | AI67: 3116.25 | AJ67: 12292.53 | AK67: 0 | AL67: 0 | AM67: 0 | AQ67: N | AS67: Juridica | AT67: Ativo | AU67: 501 | AV67: 10 | AW67: 1 | AX67: 45860 | AY67: TER/QUI/SAB/ | AZ67: 46023 | BA67: 0 | BB67: 0 | BC67: 0 | BD67: 700 | BE67: 70 | BF67: 9 | BG67: 45536 | BH67: DOM/ | BI67: 46026 | BJ67: 0 | BK67: 0 | BL67: 0 | BM67: 3.44 | BN67: 3.44 | BO67: 5252.51 | BP67: 0 | BQ67: 5252.51 | BR67: 0 | BS67: 4 | BT67: 4 | BU67: 3116.25 | BV67: 0 | BW67: 3116.25 | BX67: 0 | BY67: 0 | BZ67: 0 | CA67: 0 | CB67: 6176.47 | CC67: Lj. Conveniencia
A68: 345 | B68: 2 | C68: 198 | D68: 23.084.469/0001-51 | F68: PIZZARIA SABOR DA PI | G68: ANTONIO CARLOS ALVES FERREIRA ME | H68: RUA DEP AMADEU GOMES 203 | J68: CENTRO | K68: ACARAU | L68: CE | M68: 62.580-000 | N68: 85 99957-2751 | O68: REST./PIZZARIA/CHURR | P68: 0 | R68: 6 | S68: 39 | V68: 0 | W68: 0 | X68: 0 | Y68: 0 | Z68: 0 | AA68: 0 | AB68: 0 | AC68: 0 | AD68: Nao | AE68: Nao | AF68: 45518 | AG68: 46008 | AH68: 460.43 | AI68: 514.46 | AJ68: 1381.3 | AK68: 0 | AL68: 0 | AM68: 0 | AQ68: N | AS68: Juridica | AT68: Ativo | AU68: 101 | AV68: 10 | AW68: 1 | AX68: 45860 | AY68: TER/ | AZ68: 46028 | BA68: 0 | BB68: 0 | BC68: 0 | BD68: 700 | BE68: 70 | BF68: 9 | BG68: 45536 | BH68: DOM/ | BI68: 46026 | BJ68: 0 | BK68: 0 | BL68: 0 | BM68: 0 | BN68: 0 | BO68: 0 | BP68: 436.48 | BQ68: 436.48 | BR68: 0 | BS68: 0 | BT68: 0 | BU68: 0 | BV68: 514.46 | BW68: 514.46 | BX68: 0 | BY68: 0 | BZ68: 0 | CA68: 0 | CB68: 288.94 | CC68: Rota
A69: 345 | B69: 2 | C69: 199 | D69: 012.984.653-89 | F69: MERCADINHO SEU ANTON | G69: FRANCISCO ANTONIO DE SOUSA | H69: R R PRESIDENTE JUSCELINO SN | J69: BRASILIA | K69: CRUZ | L69: CE | M69: 62.595-000 | N69: 08 89632-7616 | O69: ARMAZEM/MERCEARIA | P69: 0 | R69: 6 | S69: 39 | V69: 0 | W69: 0 | X69: 0 | Y69: 0 | Z69: 0 | AA69: 0 | AB69: 0 | AC69: 0 | AD69: Nao | AE69: Nao | AF69: 45518 | AG69: 46013 | AH69: 19.44 | AI69: 19.44 | AJ69: 19.44 | AK69: 0 | AL69: 0 | AM69: 0 | AQ69: N | AS69: Fisica | AT69: Ativo | AU69: 105 | AV69: 10 | AW69: 1 | AX69: 45814 | AY69: SEX/ | AZ69: 46024 | BA69: 0 | BB69: 0 | BC69: 0 | BD69: 700 | BE69: 70 | BF69: 9 | BG69: 45536 | BH69: DOM/ | BI69: 46026 | BJ69: 0 | BK69: 0 | BL69: 0 | BM69: 0 | BN69: 0 | BO69: 0 | BP69: 0 | BQ69: 0 | BR69: 0 | BS69: 0 | BT69: 0 | BU69: 0 | BV69: 19.44 | BW69: 19.44 | BX69: 0 | BY69: 0 | BZ69: 0 | CA69: 0 | CB69: 87.18 | CC69: TRAD
A70: 345 | B70: 2 | C70: 200 | D70: 05.436.145/0001-53 | F70: MERCANTIL BARATEIRO | G70: ANTONIO FLAVIO DA SILVEIRA ME | H70: RUA R CEL TEIXEIRA PINTO 350 | J70: CENTRO | K70: CRUZ | L70: CE | M70: 62.595-000 | N70: 08 89938-4607 | O70: ARMAZEM/MERCEARIA | P70: 0 | R70: 6 | S70: 44 | V70: 0 | W70: 0 | X70: 0 | Y70: 0 | Z70: 0 | AA70: 0 | AB70: 0 | AC70: 0 | AD70: Nao | AE70: Nao | AF70: 45518 | AG70: 46013 | AH70: 687.47 | AI70: 1107.73 | AJ70: 5499.76 | AK70: 0 | AL70: 0 | AM70: 0 | AQ70: N | AS70: Juridica | AT70: Ativo | AU70: 105 | AV70: 10 | AW70: 1 | AX70: 45849 | AY70: SEX/ | AZ70: 46024 | BA70: 0 | BB70: 0 | BC70: 0 | BD70: 700 | BE70: 70 | BF70: 9 | BG70: 45536 | BH70: DOM/ | BI70: 46026 | BJ70: 0 | BK70: 0 | BL70: 0 | BM70: 0 | BN70: 0 | BO70: 0 | BP70: 1785.22 | BQ70: 1785.22 | BR70: 0 | BS70: 0 | BT70: 0 | BU70: 0 | BV70: 2553.72 | BW70: 2553.72 | BX70: 0 | BY70: 0 | BZ70: 0 | CA70: 0 | CB70: 1574.73 | CC70: TRAD
A71: 345 | B71: 2 | C71: 201 | D71: 11.959.925/0001-80 | F71: MERCADINHO ANA JULIA | G71: JOSE CLEBER VASCONCELOS ME | H71: RUA BERNARDINO ALBUQUERQUE 233 | J71: CENTRO | K71: CRUZ | L71: CE | M71: 62.595-000 | N71: 88 99949-1622 | O71: ARMAZEM/MERCEARIA | P71: 0 | R71: 6 | S71: 45 | V71: 0 | W71: 0 | X71: 0 | Y71: 0 | Z71: 0 | AA71: 0 | AB71: 0 | AC71: 0 | AD71: Nao | AE71: Nao | AF71: 45518 | AG71: 45990 | AH71: 52.73 | AI71: 53.28 | AJ71: 105.47 | AK71: 0 | AL71: 0 | AM71: 0 | AQ71: N | AS71: Juridica | AT71: Ativo | AU71: 105 | AV71: 10 | AW71: 1 | AX71: 45849 | AY71: SEX/ | AZ71: 46024 | BA71: 0 | BB71: 0 | BC71: 0 | BD71: 700 | BE71: 70 | BF71: 9 | BG71: 45536 | BH71: DOM/ | BI71: 46026 | BJ71: 0 | BK71: 0 | BL71: 0 | BM71: 0 | BN71: 0 | BO71: 0 | BP71: 53.28 | BQ71: 53.28 | BR71: 0 | BS71: 0 | BT71: 0 | BU71: 0 | BV71: 0 | BW71: 0 | BX71: 0 | BY71: 0 | BZ71: 0 | CA71: 0 | CB71: 45.15 | CC71: TRAD
A72: 345 | B72: 2 | C72: 202 | D72: 060.127.943-39 | F72: MERCADINHO DO BARROS | G72: JOSE BARROSO RODRIGUES | H72: R ALMECEGAS SN | J72: ALMACEGAS | K72: ACARAU | L72: CE | M72: 62.580-000 | N72: 88 99682-2385 | O72: ARMAZEM/MERCEARIA | P72: 0 | R72: 6 | S72: 39 | V72: 0 | W72: 0 | X72: 0 | Y72: 0 | Z72: 0 | AA72: 0 | AB72: 0 | AC72: 0 | AD72: Nao | AE72: Nao | AF72: 45518 | AG72: 46021 | AH72: 138.25 | AI72: 177.9 | AJ72: 691.27 | AK72: 0 | AL72: 0 | AM72: 0 | AQ72: N | AS72: Fisica | AT72: Ativo | AU72: 101 | AV72: 10 | AW72: 1 | AX72: 45859 | AY72: SEG/ | AZ72: 46027 | BA72: 0 | BB72: 0 | BC72: 0 | BD72: 700 | BE72: 70 | BF72: 9 | BG72: 45536 | BH72: DOM/ | BI72: 46026 | BJ72: 0 | BK72: 0 | BL72: 0 | BM72: 0 | BN72: 0 | BO72: 0 | BP72: 229.98 | BQ72: 229.98 | BR72: 0 | BS72: 0 | BT72: 0 | BU72: 0 | BV72: 283.39 | BW72: 283.39 | BX72: 0 | BY72: 0 | BZ72: 0 | CA72: 0 | CB72: 203.98 | CC72: TRAD
A73: 345 | B73: 2 | C73: 204 | D73: 13.757.852/0001-70 | F73: PANIFICADORA E MERCA | G73: FRANCISCO DAS CHAGAS FARIAS FILHO | H73: RUA TANCREDO NEVES 266 | J73: CENTRO | K73: CRUZ | L73: CE | M73: 62.595-000 | N73: 88 99980-0790 | O73: ARMAZEM/MERCEARIA | P73: 0 | R73: 6 | S73: 43 | V73: 0 | W73: 0 | X73: 0 | Y73: 0 | Z73: 0 | AA73: 0 | AB73: 0 | AC73: 0 | AD73: Nao | AE73: Nao | AF73: 45518 | AG73: 45990 | AH73: 539.48 | AI73: 649.26 | AJ73: 1078.96 | AK73: 0 | AL73: 0 | AM73: 0 | AQ73: N | AS73: Juridica | AT73: Ativo | AU73: 105 | AV73: 10 | AW73: 1 | AX73: 45849 | AY73: SEX/ | AZ73: 46024 | BA73: 0 | BB73: 0 | BC73: 0 | BD73: 700 | BE73: 70 | BF73: 9 | BG73: 45536 | BH73: DOM/ | BI73: 46026 | BJ73: 0 | BK73: 0 | BL73: 0 | BM73: 0 | BN73: 0 | BO73: 0 | BP73: 649.26 | BQ73: 649.26 | BR73: 0 | BS73: 0 | BT73: 0 | BU73: 0 | BV73: 0 | BW73: 0 | BX73: 0 | BY73: 0 | BZ73: 0 | CA73: 0 | CB73: 512.15 | CC73: TRAD
A74: 345 | B74: 2 | C74: 205 | D74: 236.187.873-91 | F74: MERCADINHO SAO FRANC | G74: FRANCISCO RIOS ROCHA FILHO | H74: R SANTO ANTONIO SN | J74: OUTRA BANDA | K74: ACARAU | L74: CE | M74: 62.580-000 | N74: 88 99691-6087 | O74: ARMAZEM/MERCEARIA | P74: 0 | R74: 6 | S74: 40 | V74: 0 | W74: 0 | X74: 0 | Y74: 0 | Z74: 0 | AA74: 0 | AB74: 0 | AC74: 0 | AD74: Nao | AE74: Nao | AF74: 45518 | AG74: 46010 | AH74: 355.11 | AI74: 466.81 | AJ74: 2840.95 | AK74: 0 | AL74: 0 | AM74: 0 | AQ74: N | AS74: Fisica | AT74: Ativo | AU74: 101 | AV74: 10 | AW74: 1 | AX74: 45841 | AY74: QUI/ | AZ74: 46023 | BA74: 0 | BB74: 0 | BC74: 0 | BD74: 700 | BE74: 70 | BF74: 9 | BG74: 45536 | BH74: DOM/ | BI74: 46026 | BJ74: 0 | BK74: 0 | BL74: 0 | BM74: 0 | BN74: 0 | BO74: 0 | BP74: 1060.39 | BQ74: 1060.39 | BR74: 0 | BS74: 0 | BT74: 0 | BU74: 0 | BV74: 791.66 | BW74: 791.66 | BX74: 0 | BY74: 0 | BZ74: 0 | CA74: 0 | CB74: 847.86 | CC74: TRAD
A75: 345 | B75: 2 | C75: 206 | D75: 764.754.093-91 | F75: MERCEARIA DO MARCIO | G75: MARCIO JOSE DO NASCIMENTO | H75: R R PRESIDENTE JUSCELINO SN | J75: BRASILIA | K75: CRUZ | L75: CE | M75: 62.595-000 | N75: 08 89926-8403 | O75: ARMAZEM/MERCEARIA | P75: 0 | R75: 6 | S75: 41 | V75: 0 | W75: 0 | X75: 0 | Y75: 0 | Z75: 0 | AA75: 0 | AB75: 0 | AC75: 0 | AD75: Nao | AE75: Nao | AF75: 45518 | AG75: 46013 | AH75: 101.42 | AI75: 101.42 | AJ75: 101.42 | AK75: 0 | AL75: 0 | AM75: 0 | AQ75: N | AS75: Fisica | AT75: Ativo | AU75: 105 | AV75: 10 | AW75: 1 | AX75: 45815 | AY75: SAB/ | AZ75: 46025 | BA75: 0 | BB75: 0 | BC75: 0 | BD75: 700 | BE75: 70 | BF75: 9 | BG75: 45536 | BH75: DOM/ | BI75: 46026 | BJ75: 0 | BK75: 0 | BL75: 0 | BM75: 0 | BN75: 0 | BO75: 0 | BP75: 0 | BQ75: 0 | BR75: 0 | BS75: 0 | BT75: 0 | BU75: 0 | BV75: 101.42 | BW75: 101.42 | BX75: 0 | BY75: 0 | BZ75: 0 | CA75: 0 | CB75: 35.46 | CC75: TRAD
A76: 345 | B76: 2 | C76: 208 | D76: 148.755.808-27 | F76: MERCANTIL JC CURRAL | G76: JOSE CLEUDES DOS SANTOS | H76: RUA CURRAL VELHO 10000 | I76: CURRAL DE CIMA S/N | J76: CURRAL VELHO | K76: ACARAU | L76: CE | M76: 62.580-000 | N76: 88 99967-5430 | O76: ARMAZEM/MERCEARIA | P76: 0 | R76: 6 | S76: 40 | V76: 0 | W76: 0 | X76: 0 | Y76: 0 | Z76: 0 | AA76: 0 | AB76: 0 | AC76: 0 | AD76: Nao | AE76: Nao | AF76: 45518 | AG76: 46014 | AH76: 532.48 | AI76: 926.68 | AJ76: 2129.95 | AK76: 0 | AL76: 379.45 | AM76: 0 | AQ76: N | AS76: Fisica | AT76: Ativo | AU76: 104 | AV76: 10 | AW76: 1 | AX76: 45859 | AY76: SEG/ | AZ76: 46027 | BA76: 0 | BB76: 0 | BC76: 0 | BD76: 700 | BE76: 70 | BF76: 9 | BG76: 45536 | BH76: DOM/ | BI76: 46026 | BJ76: 0 | BK76: 0 | BL76: 0 | BM76: 0 | BN76: 0 | BO76: 0 | BP76: 926.68 | BQ76: 926.68 | BR76: 0 | BS76: 0 | BT76: 0 | BU76: 0 | BV76: 1203.27 | BW76: 1203.27 | BX76: 0 | BY76: 0 | BZ76: 0 | CA76: 0 | CB76: 786.34 | CC76: TRAD
A77: 345 | B77: 2 | C77: 210 | D77: 477.043.488-09 | F77: BAR DA MANGUEIRA TU | G77: KAUAN TAYLON DE VASCONCELOS | H77: AV TUCUNS 10000 | I77: S N | J77: TUCUNS | K77: CRUZ | L77: CE | M77: 62.595-000 | N77: 88 99606-6606 | O77: BAR/BARZINHO | P77: 0 | R77: 6 | S77: 35 | V77: 0 | W77: 0 | X77: 0 | Y77: 0 | Z77: 0 | AA77: 0 | AB77: 0 | AC77: 0 | AD77: Nao | AE77: Nao | AF77: 45518 | AG77: 46004 | AH77: 138.08 | AI77: 153.78 | AJ77: 276.16 | AK77: 0 | AL77: 0 | AM77: 0 | AQ77: N | AS77: Fisica | AT77: Ativo | AU77: 100 | AV77: 10 | AW77: 1 | AX77: 45856 | AY77: SEX/ | AZ77: 46024 | BA77: 0 | BB77: 0 | BC77: 0 | BD77: 700 | BE77: 70 | BF77: 9 | BG77: 45536 | BH77: DOM/ | BI77: 46026 | BJ77: 0 | BK77: 0 | BL77: 0 | BM77: 0 | BN77: 0 | BO77: 0 | BP77: 122.38 | BQ77: 122.38 | BR77: 0 | BS77: 0 | BT77: 0 | BU77: 0 | BV77: 153.78 | BW77: 153.78 | BX77: 0 | BY77: 0 | BZ77: 0 | CA77: 0 | CB77: 40.79 | CC77: Rota
A78: 345 | B78: 2 | C78: 211 | D78: 025.573.793-95 | F78: MS MERCANTIL PORTEI | G78: SHIRLEY FREITAS LIMA SILVEIRA | H78: VIL PORTEIRAS 10000 | I78: S/N | J78: PORTEIRAS | K78: ACARAU | L78: CE | M78: 62.580-000 | N78: 08 89787-3518 | O78: ARMAZEM/MERCEARIA | P78: 0 | R78: 6 | S78: 40 | V78: 0 | W78: 0 | X78: 0 | Y78: 0 | Z78: 0 | AA78: 0 | AB78: 0 | AC78: 0 | AD78: Nao | AE78: Nao | AF78: 45518 | AG78: 46020 | AH78: 496.67 | AI78: 845.37 | AJ78: 4966.75 | AK78: 0 | AL78: 0 | AM78: 0 | AQ78: N | AS78: Fisica | AT78: Ativo | AU78: 100 | AV78: 10 | AW78: 1 | AX78: 45815 | AY78: SAB/ | AZ78: 46025 | BA78: 0 | BB78: 0 | BC78: 0 | BD78: 700 | BE78: 70 | BF78: 9 | BG78: 45536 | BH78: DOM/ | BI78: 46026 | BJ78: 0 | BK78: 0 | BL78: 0 | BM78: 0 | BN78: 0 | BO78: 0 | BP78: 1238.76 | BQ78: 1238.76 | BR78: 0 | BS78: 0 | BT78: 0 | BU78: 0 | BV78: 2310.47 | BW78: 2310.47 | BX78: 0 | BY78: 0 | BZ78: 0 | CA78: 0 | CB78: 1251.25 | CC78: TRAD
A79: 345 | B79: 2 | C79: 212 | D79: 066.755.093-30 | F79: MERCANTIL PEKETO PI | G79: FERNANDO FARIAS FREITAS | H79: VIL DT PITOMBEIRAS 10000 | I79: S/N | J79: PITOMBEIRAS | K79: CRUZ | L79: CE | M79: 62.595-000 | N79: 08 89841-3222 | O79: ARMAZEM/MERCEARIA | P79: 0 | R79: 6 | S79: 39 | V79: 0 | W79: 0 | X79: 0 | Y79: 7 | Z79: 0 | AA79: 0 | AB79: 0 | AC79: 0 | AD79: Sim | AE79: Nao | AF79: 45518 | AG79: 46020 | AH79: 2255.26 | AI79: 3755.1 | AJ79: 29318.43 | AK79: 0 | AL79: 0 | AM79: 0 | AQ79: N | AS79: Fisica | AT79: Ativo | AU79: 100 | AV79: 10 | AW79: 1 | AX79: 45815 | AY79: SAB/ | AZ79: 46025 | BA79: 0 | BB79: 0 | BC79: 0 | BD79: 700 | BE79: 70 | BF79: 9 | BG79: 45536 | BH79: DOM/ | BI79: 46026 | BJ79: 0 | BK79: 0 | BL79: 0 | BM79: 0 | BN79: 0 | BO79: 0 | BP79: 8341.77 | BQ79: 8341.77 | BR79: 0 | BS79: 0 | BT79: 0 | BU79: 0 | BV79: 13314.56 | BW79: 13314.56 | BX79: 0 | BY79: 0 | BZ79: 0 | CA79: 0 | CB79: 9228.66 | CC79: TRAD
A80: 345 | B80: 2 | C80: 213 | D80: 623.073.963-14 | F80: RICARDO COMERCIO AC | G80: RICARDO SEBASTIAOPASSOS | H80: RUA R CEL SALES 10000 | I80: S/N | J80: ACUDE NOVO | K80: ACARAU | L80: CE | M80: 62.580-000 | N80: 88 99861-3937 | O80: ARMAZEM/MERCEARIA | P80: 0 | R80: 6 | S80: 39 | V80: 0 | W80: 0 | X80: 0 | Y80: 0 | Z80: 0 | AA80: 0 | AB80: 0 | AC80: 0 | AD80: Nao | AE80: Nao | AF80: 45518 | AG80: 46020 | AH80: 255.16 | AI80: 321.63 | AJ80: 1275.8 | AK80: 0 | AL80: 0 | AM80: 0 | AQ80: N | AS80: Fisica | AT80: Ativo | AU80: 101 | AV80: 10 | AW80: 1 | AX80: 45535 | AY80: SAB/ | AZ80: 46025 | BA80: 0 | BB80: 0 | BC80: 0 | BD80: 700 | BE80: 70 | BF80: 9 | BG80: 45536 | BH80: DOM/ | BI80: 46026 | BJ80: 0 | BK80: 0 | BL80: 0 | BM80: 0 | BN80: 0 | BO80: 0 | BP80: 288.26 | BQ80: 288.26 | BR80: 0 | BS80: 0 | BT80: 0 | BU80: 0 | BV80: 828.02 | BW80: 828.02 | BX80: 0 | BY80: 0 | BZ80: 0 | CA80: 0 | CB80: 512.2 | CC80: TRAD
A81: 345 | B81: 2 | C81: 215 | D81: 189.963.963-20 | F81: S5 - MERCEARIA DEHON | G81: UMBELINA LAURA FONTENELE | H81: R CURRAL VELHO SN | J81: CURRAL VELHO | K81: ACARAU | L81: CE | M81: 62.580-000 | N81: 88 99857-2162 | O81: ARMAZEM/MERCEARIA | P81: 0 | R81: 6 | S81: 41 | V81: 0 | W81: 0 | X81: 0 | Y81: 0 | Z81: 0 | AA81: 0 | AB81: 0 | AC81: 0 | AD81: Nao | AE81: Nao | AF81: 45518 | AG81: 46014 | AH81: 1036.64 | AI81: 6507 | AJ81: 9329.79 | AK81: 0 | AL81: 1146 | AM81: 0 | AQ81: N | AS81: Fisica | AT81: Ativo | AU81: 104 | AV81: 10 | AW81: 1 | AX81: 45859 | AY81: SEG/ | AZ81: 46027 | BA81: 0 | BB81: 0 | BC81: 0 | BD81: 700 | BE81: 70 | BF81: 9 | BG81: 45536 | BH81: DOM/ | BI81: 46026 | BJ81: 0 | BK81: 0 | BL81: 0 | BM81: 0 | BN81: 0 | BO81: 0 | BP81: 834.57 | BQ81: 834.57 | BR81: 0 | BS81: 0 | BT81: 0 | BU81: 0 | BV81: 1729.94 | BW81: 1729.94 | BX81: 0 | BY81: 0 | BZ81: 0 | CA81: 0 | CB81: 4253.63 | CC81: TRAD
A82: 345 | B82: 2 | C82: 219 | D82: 781.986.153-34 | F82: IDEAL LANCHES E ACAI | G82: JOSE ROBERTO SILVA FLOR | H82: DT DT LAGOA DO CARNEIRO SN | J82: LAGOA DO CARNEIRO | K82: ACARAU | L82: CE | M82: 62.580-000 | N82: 08 88129-8522 | O82: LANCHONETE/PASTELARI | P82: 0 | R82: 6 | S82: 37 | V82: 0 | W82: 0 | X82: 0 | Y82: 0 | Z82: 0 | AA82: 0 | AB82: 0 | AC82: 0 | AD82: Nao | AE82: Nao | AF82: 45518 | AG82: 46011 | AH82: 404.38 | AI82: 842.73 | AJ82: 2426.28 | AK82: 0 | AL82: 0 | AM82: 0 | AQ82: N | AS82: Fisica | AT82: Ativo | AU82: 102 | AV82: 10 | AW82: 1 | AX82: 45842 | AY82: SEX/ | AZ82: 46024 | BA82: 0 | BB82: 0 | BC82: 0 | BD82: 700 | BE82: 70 | BF82: 9 | BG82: 45536 | BH82: DOM/ | BI82: 46026 | BJ82: 0 | BK82: 0 | BL82: 0 | BM82: 0 | BN82: 0 | BO82: 0 | BP82: 779.68 | BQ82: 779.68 | BR82: 0 | BS82: 0 | BT82: 0 | BU82: 0 | BV82: 842.73 | BW82: 842.73 | BX82: 0 | BY82: 0 | BZ82: 0 | CA82: 0 | CB82: 728.12 | CC82: Rota
A83: 345 | B83: 2 | C83: 220 | D83: 08.270.152/0001-16 | F83: MERCEARIA O TADEU A | G83: JOSE TADEU FILHO | H83: R Padre joao Batista Pereira SN | J83: MORADA NOVA | K83: ACARAU | L83: CE | M83: 62.580-000 | N83: 88 99663-7029 | O83: ARMAZEM/MERCEARIA | P83: 0 | R83: 6 | S83: 43 | V83: 0 | W83: 0 | X83: 0 | Y83: 0 | Z83: 0 | AA83: 0 | AB83: 0 | AC83: 0 | AD83: Nao | AE83: Nao | AF83: 45518 | AG83: 46018 | AH83: 234.55 | AI83: 352.72 | AJ83: 1876.43 | AK83: 0 | AL83: 0 | AM83: 0 | AQ83: N | AS83: Juridica | AT83: Ativo | AU83: 101 | AV83: 10 | AW83: 1 | AX83: 45812 | AY83: QUA/ | AZ83: 46022 | BA83: 0 | BB83: 0 | BC83: 0 | BD83: 700 | BE83: 70 | BF83: 9 | BG83: 45536 | BH83: DOM/ | BI83: 46026 | BJ83: 0 | BK83: 0 | BL83: 0 | BM83: 0 | BN83: 0 | BO83: 0 | BP83: 516.37 | BQ83: 516.37 | BR83: 0 | BS83: 0 | BT83: 0 | BU83: 0 | BV83: 1043.97 | BW83: 1043.97 | BX83: 0 | BY83: 0 | BZ83: 0 | CA83: 0 | CB83: 347.08 | CC83: TRAD
A84: 345 | B84: 2 | C84: 221 | D84: 324.243.533-87 | F84: RANCHO DA ROCA | G84: JOSE ZILMAR ARAUJO | H84: RUA RUA CEARA 936 | J84: CORREGO DO REINALDO | K84: BELA CRUZ | L84: CE | M84: 62.570-000 | N84: 08 89986-3593 | O84: BAR/BARZINHO | P84: 0 | R84: 6 | S84: 36 | V84: 0 | W84: 0 | X84: 0 | Y84: 0 | Z84: 0 | AA84: 0 | AB84: 0 | AC84: 0 | AD84: Sim | AE84: Nao | AF84: 45518 | AG84: 46017 | AH84: 325.4 | AI84: 481.93 | AJ84: 4230.3 | AK84: 0 | AL84: 0 | AM84: 0 | AQ84: N | AS84: Fisica | AT84: Ativo | AU84: 102 | AV84: 10 | AW84: 1 | AX84: 45832 | AY84: TER/ | AZ84: 46028 | BA84: 0 | BB84: 0 | BC84: 0 | BD84: 700 | BE84: 70 | BF84: 9 | BG84: 45536 | BH84: DOM/ | BI84: 46026 | BJ84: 0 | BK84: 0 | BL84: 0 | BM84: 0 | BN84: 0 | BO84: 0 | BP84: 1100.77 | BQ84: 1100.77 | BR84: 0 | BS84: 0 | BT84: 0 | BU84: 0 | BV84: 1532.65 | BW84: 1532.65 | BX84: 0 | BY84: 0 | BZ84: 0 | CA84: 0 | CB84: 1199.38 | CC84: Rota
A85: 345 | B85: 2 | C85: 222 | D85: 726.350.963-68 | F85: PADARIA SANTO EXPEDI | G85: FRANCISCO DE ASSIS MORAIS | H85: RUA JOSE MILTON DE OLIVEIRA 1041 | J85: CORREGO DO REINALDO | K85: BELA CRUZ | L85: CE | M85: 62.570-000 | N85: 08 89728-9661 | O85: PADARIA/CONFEITARIA | P85: 0 | R85: 6 | S85: 29 | V85: 1000 | W85: 302.12 | X85: 697.88 | Y85: 7 | Z85: 0 | AA85: 7 | AB85: 1 | AC85: 25 | AD85: Nao | AE85: Nao | AF85: 45518 | AG85: 46017 | AH85: 266.09 | AI85: 349.47 | AJ85: 2128.75 | AK85: 0 | AL85: 302.12 | AM85: 0 | AQ85: N | AS85: Fisica | AT85: Ativo | AU85: 102 | AV85: 10 | AW85: 1 | AX85: 45811 | AY85: TER/ | AZ85: 46028 | BA85: 0 | BB85: 0 | BC85: 0 | BD85: 700 | BE85: 70 | BF85: 9 | BG85: 45536 | BH85: DOM/ | BI85: 46026 | BJ85: 0 | BK85: 0 | BL85: 0 | BM85: 7 | BN85: 7 | BO85: 475.33 | BP85: 0 | BQ85: 475.33 | BR85: 0 | BS85: 6.07 | BT85: 3.31 | BU85: 651.59 | BV85: 544.99 | BW85: 1196.58 | BX85: 0 | BY85: 0 | BZ85: 0 | CA85: 0 | CB85: 345.47 | CC85: TRAD
A86: 345 | B86: 2 | C86: 223 | D86: 057.224.243-31 | F86: MERC VALDERI LAGOA | G86: FRANCISCO ALEX SENA MEDEIROS | H86: LGA LAGOA DO CARNEIRO SN | I86: No Valdeci | J86: LAGOA DO CARNEIRO | K86: ACARAU | L86: CE | M86: 62.580-000 | N86: 08 89936-1480 | O86: ARMAZEM/MERCEARIA | P86: 0 | R86: 6 | S86: 40 | V86: 0 | W86: 0 | X86: 0 | Y86: 0 | Z86: 0 | AA86: 0 | AB86: 0 | AC86: 0 | AD86: Nao | AE86: Nao | AF86: 45518 | AG86: 46020 | AH86: 1395.37 | AI86: 2199.5 | AJ86: 8372.27 | AK86: 0 | AL86: 0 | AM86: 0 | AQ86: N | AS86: Fisica | AT86: Ativo | AU86: 102 | AV86: 10 | AW86: 1 | AX86: 45842 | AY86: SEX/ | AZ86: 46024 | BA86: 0 | BB86: 0 | BC86: 0 | BD86: 700 | BE86: 70 | BF86: 9 | BG86: 45536 | BH86: DOM/ | BI86: 46026 | BJ86: 0 | BK86: 0 | BL86: 0 | BM86: 0 | BN86: 0 | BO86: 0 | BP86: 3303.7 | BQ86: 3303.7 | BR86: 0 | BS86: 0 | BT86: 0 | BU86: 0 | BV86: 4079.09 | BW86: 4079.09 | BX86: 0 | BY86: 0 | BZ86: 0 | CA86: 0 | CB86: 2480.42 | CC86: TRAD
A87: 345 | B87: 2 | C87: 225 | D87: 051.600.123-03 | F87: MERC EUGENIO CAUASS | G87: MILQUESEDESK SILVA DOS SANTOS | H87: RUA CAUASSU 10000 | J87: CAUASSU | K87: ACARAU | L87: CE | M87: 62.580-000 | N87: 88 99713-7889 | O87: ARMAZEM/MERCEARIA | P87: 0 | R87: 6 | S87: 40 | V87: 0 | W87: 0 | X87: 0 | Y87: 0 | Z87: 0 | AA87: 0 | AB87: 0 | AC87: 0 | AD87: Nao | AE87: Nao | AF87: 45518 | AG87: 46007 | AH87: 717.56 | AI87: 1034.34 | AJ87: 7175.61 | AK87: 0 | AL87: 553.29 | AM87: 0 | AQ87: N | AS87: Fisica | AT87: Ativo | AU87: 104 | AV87: 10 | AW87: 1 | AX87: 45537 | AY87: SEG/ | AZ87: 46027 | BA87: 0 | BB87: 0 | BC87: 0 | BD87: 700 | BE87: 70 | BF87: 9 | BG87: 45536 | BH87: DOM/ | BI87: 46026 | BJ87: 0 | BK87: 0 | BL87: 0 | BM87: 0 | BN87: 0 | BO87: 0 | BP87: 2380.8 | BQ87: 2380.8 | BR87: 0 | BS87: 0 | BT87: 0 | BU87: 0 | BV87: 2698.23 | BW87: 2698.23 | BX87: 0 | BY87: 0 | BZ87: 0 | CA87: 0 | CB87: 2205.86 | CC87: TRAD
A88: 345 | B88: 2 | C88: 226 | D88: 465.853.543-20 | F88: GL VARIEDADES LAGOA | G88: RAIMUNDO LUIS DE SOUSA | H88: RUA DT LAGOA DO CARNEIRO 1440 | J88: LAGOA DO CARNEIRO | K88: ACARAU | L88: CE | M88: 62.580-000 | N88: 88 98161-6515 | O88: ARMAZEM/MERCEARIA | P88: 0 | R88: 6 | S88: 40 | V88: 0 | W88: 0 | X88: 0 | Y88: 0 | Z88: 0 | AA88: 0 | AB88: 0 | AC88: 0 | AD88: Nao | AE88: Nao | AF88: 45518 | AG88: 46020 | AH88: 769.9 | AI88: 1451.15 | AJ88: 8468.96 | AK88: 0 | AL88: 0 | AM88: 0 | AQ88: N | AS88: Fisica | AT88: Ativo | AU88: 102 | AV88: 10 | AW88: 1 | AX88: 45849 | AY88: SEX/ | AZ88: 46024 | BA88: 0 | BB88: 0 | BC88: 0 | BD88: 700 | BE88: 70 | BF88: 9 | BG88: 45536 | BH88: DOM/ | BI88: 46026 | BJ88: 0 | BK88: 0 | BL88: 0 | BM88: 0 | BN88: 0 | BO88: 0 | BP88: 3342.68 | BQ88: 3342.68 | BR88: 0 | BS88: 0 | BT88: 0 | BU88: 0 | BV88: 3469.75 | BW88: 3469.75 | BX88: 0 | BY88: 0 | BZ88: 0 | CA88: 0 | CB88: 2064.4 | CC88: TRAD
A89: 345 | B89: 2 | C89: 227 | D89: 070.440.227-07 | F89: BAR E MERCEARIA RECA | G89: RAIMUNDO ADRIANO DE ANDRADE | H89: RUA CELSOLANDIA 10000 | I89: EM FRENTE AO COLEGIO CAROLINO | J89: CELSOLANDIA | K89: ACARAU | L89: CE | M89: 62.580-000 | N89: 88 99988-5610 | O89: BAR/BARZINHO | P89: 0 | R89: 6 | S89: 36 | V89: 0 | W89: 0 | X89: 0 | Y89: 0 | Z89: 0 | AA89: 0 | AB89: 0 | AC89: 0 | AD89: Nao | AE89: Nao | AF89: 45518 | AG89: 46020 | AH89: 460.35 | AI89: 919.32 | AJ89: 6444.96 | AK89: 0 | AL89: 0 | AM89: 0 | AQ89: N | AS89: Fisica | AT89: Ativo | AU89: 101 | AV89: 10 | AW89: 1 | AX89: 45842 | AY89: SEX/ | AZ89: 46024 | BA89: 0 | BB89: 0 | BC89: 0 | BD89: 700 | BE89: 70 | BF89: 9 | BG89: 45536 | BH89: DOM/ | BI89: 46026 | BJ89: 0 | BK89: 0 | BL89: 0 | BM89: 0 | BN89: 0 | BO89: 0 | BP89: 2673.6 | BQ89: 2673.6 | BR89: 0 | BS89: 0 | BT89: 0 | BU89: 0 | BV89: 2052.35 | BW89: 2052.35 | BX89: 0 | BY89: 0 | BZ89: 0 | CA89: 0 | CB89: 1876.97 | CC89: Rota
A90: 345 | B90: 2 | C90: 228 | D90: 007.488.193-04 | F90: LUAN BEBIDAS ACARAU | G90: VIVIANE MOURA GOMES | H90: RUA RUA CAPITAO ANTONIO RAIMUNDO 356 | J90: OUTRA BANDA | K90: ACARAU | L90: CE | M90: 62.580-000 | N90: 88 99729-6341 | O90: DEPOSITO DE BEBIDAS | P90: 0 | R90: 6 | S90: 39 | V90: 0 | W90: 0 | X90: 0 | Y90: 0 | Z90: 0 | AA90: 0 | AB90: 0 | AC90: 0 | AD90: Nao | AE90: Nao | AF90: 45518 | AG90: 46010 | AH90: 152.91 | AI90: 190.01 | AJ90: 305.83 | AK90: 0 | AL90: 0 | AM90: 0 | AQ90: N | AS90: Fisica | AT90: Ativo | AU90: 101 | AV90: 10 | AW90: 1 | AX90: 45813 | AY90: QUI/ | AZ90: 46023 | BA90: 0 | BB90: 0 | BC90: 0 | BD90: 700 | BE90: 70 | BF90: 9 | BG90: 45536 | BH90: DOM/ | BI90: 46026 | BJ90: 0 | BK90: 0 | BL90: 0 | BM90: 0 | BN90: 0 | BO90: 0 | BP90: 115.82 | BQ90: 115.82 | BR90: 0 | BS90: 0 | BT90: 0 | BU90: 0 | BV90: 190.01 | BW90: 190.01 | BX90: 0 | BY90: 0 | BZ90: 0 | CA90: 0 | CB90: 119.21 | CC90: SUB
A91: 345 | B91: 2 | C91: 229 | D91: 324.248.413-49 | F91: MERC CHEGA MAIS LAG | G91: MANOEL GILBERTO SILVEIRA | H91: RUA LAGOA DO CARNEIRO 10000 | J91: LAGOA DO CARNEIRO | K91: ACARAU | L91: CE | M91: 62.580-000 | N91: 08 88137-2491 | O91: ARMAZEM/MERCEARIA | P91: 0 | R91: 6 | S91: 40 | V91: 0 | W91: 0 | X91: 0 | Y91: 0 | Z91: 0 | AA91: 0 | AB91: 0 | AC91: 0 | AD91: Nao | AE91: Nao | AF91: 45518 | AG91: 46019 | AH91: 1962.57 | AI91: 3008.23 | AJ91: 15700.61 | AK91: 0 | AL91: 0 | AM91: 0 | AQ91: N | AS91: Fisica | AT91: Ativo | AU91: 102 | AV91: 10 | AW91: 1 | AX91: 45842 | AY91: SEX/ | AZ91: 46024 | BA91: 0 | BB91: 0 | BC91: 0 | BD91: 700 | BE91: 70 | BF91: 9 | BG91: 45536 | BH91: DOM/ | BI91: 46026 | BJ91: 0 | BK91: 0 | BL91: 0 | BM91: 0 | BN91: 0 | BO91: 0 | BP91: 5867.22 | BQ91: 5867.22 | BR91: 0 | BS91: 0 | BT91: 0 | BU91: 0 | BV91: 4771.96 | BW91: 4771.96 | BX91: 0 | BY91: 0 | BZ91: 0 | CA91: 0 | CB91: 5310.71 | CC91: TRAD
A92: 345 | B92: 2 | C92: 230 | D92: 675.013.623-00 | F92: MERC AROLDO LAGOA D | G92: FRANCISCO AROLDO ARAUJO | H92: DT DT LAGOA DO CARNEIRO SN | J92: LAGOA DO CARNEIRO | K92: ACARAU | L92: CE | M92: 62.580-000 | N92: 08 88122-9492 | O92: ARMAZEM/MERCEARIA | P92: 0 | R92: 6 | S92: 40 | V92: 0 | W92: 0 | X92: 0 | Y92: 0 | Z92: 0 | AA92: 0 | AB92: 0 | AC92: 0 | AD92: Nao | AE92: Nao | AF92: 45518 | AG92: 46020 | AH92: 556.09 | AI92: 1308.48 | AJ92: 4448.75 | AK92: 0 | AL92: 0 | AM92: 0 | AQ92: N | AS92: Fisica | AT92: Ativo | AU92: 102 | AV92: 10 | AW92: 1 | AX92: 45814 | AY92: SEX/ | AZ92: 46024 | BA92: 0 | BB92: 0 | BC92: 0 | BD92: 700 | BE92: 70 | BF92: 9 | BG92: 45536 | BH92: DOM/ | BI92: 46026 | BJ92: 0 | BK92: 0 | BL92: 0 | BM92: 0 | BN92: 0 | BO92: 0 | BP92: 2063.63 | BQ92: 2063.63 | BR92: 0 | BS92: 0 | BT92: 0 | BU92: 0 | BV92: 1766.84 | BW92: 1766.84 | BX92: 0 | BY92: 0 | BZ92: 0 | CA92: 0 | CB92: 1245.92 | CC92: TRAD
A93: 345 | B93: 2 | C93: 231 | D93: 055.159.298-29 | F93: MERC SAO PEDRO LAGO | G93: JOSE ARMANDO DE ARAUJO | H93: RUA DT LAGOA DO CARNEIRO 10000 | J93: LAGOA DO CARNEIRO | K93: ACARAU | L93: CE | M93: 62.580-000 | N93: 08 88195-7946 | O93: ARMAZEM/MERCEARIA | P93: 0 | R93: 6 | S93: 40 | V93: 0 | W93: 0 | X93: 0 | Y93: 0 | Z93: 0 | AA93: 0 | AB93: 0 | AC93: 0 | AD93: Nao | AE93: Nao | AF93: 45518 | AG93: 46020 | AH93: 392.99 | AI93: 521.26 | AJ93: 4322.96 | AK93: 0 | AL93: 0 | AM93: 0 | AQ93: N | AS93: Fisica | AT93: Ativo | AU93: 102 | AV93: 10 | AW93: 1 | AX93: 45842 | AY93: SEX/ | AZ93: 46024 | BA93: 0 | BB93: 0 | BC93: 0 | BD93: 700 | BE93: 70 | BF93: 9 | BG93: 45536 | BH93: DOM/ | BI93: 46026 | BJ93: 0 | BK93: 0 | BL93: 0 | BM93: 0 | BN93: 0 | BO93: 0 | BP93: 1608.47 | BQ93: 1608.47 | BR93: 0 | BS93: 0 | BT93: 0 | BU93: 0 | BV93: 1329.63 | BW93: 1329.63 | BX93: 0 | BY93: 0 | BZ93: 0 | CA93: 0 | CB93: 1343.36 | CC93: TRAD
A94: 345 | B94: 2 | C94: 233 | D94: 707.647.353-49 | F94: BAR O ROBERTO MACAJ | G94: CARLOS ALBERTO DOS SANTOS | H94: VIL MACAJUBA 51 | J94: MACAJUBA | K94: ACARAU | L94: CE | M94: 62.580-000 | N94: 08 89952-1834 | O94: BAR/BARZINHO | P94: 0 | R94: 6 | S94: 36 | V94: 0 | W94: 0 | X94: 0 | Y94: 0 | Z94: 0 | AA94: 0 | AB94: 0 | AC94: 0 | AD94: Nao | AE94: Nao | AF94: 45518 | AG94: 46020 | AH94: 518.52 | AI94: 808.13 | AJ94: 5703.73 | AK94: 0 | AL94: 0 | AM94: 0 | AQ94: N | AS94: Fisica | AT94: Ativo | AU94: 101 | AV94: 10 | AW94: 1 | AX94: 45842 | AY94: SEX/ | AZ94: 46024 | BA94: 0 | BB94: 0 | BC94: 0 | BD94: 700 | BE94: 70 | BF94: 9 | BG94: 45536 | BH94: DOM/ | BI94: 46026 | BJ94: 0 | BK94: 0 | BL94: 0 | BM94: 0 | BN94: 0 | BO94: 0 | BP94: 2311.38 | BQ94: 2311.38 | BR94: 0 | BS94: 0 | BT94: 0 | BU94: 0 | BV94: 1994.24 | BW94: 1994.24 | BX94: 0 | BY94: 0 | BZ94: 0 | CA94: 0 | CB94: 1973.71 | CC94: Rota
A95: 345 | B95: 2 | C95: 234 | D95: 22.623.737/0001-01 | F95: MERC MARCELO LAGOA | G95: JOSE MARCELO LOPES ME | H95: RUA DT LAGOA DO CANEMA 10000 | J95: LAGOA DO CANEMA | K95: ACARAU | L95: CE | M95: 62.580-000 | N95: 08 89765-1619 | O95: ARMAZEM/MERCEARIA | P95: 0 | R95: 6 | S95: 44 | V95: 0 | W95: 0 | X95: 0 | Y95: 0 | Z95: 0 | AA95: 0 | AB95: 0 | AC95: 0 | AD95: Nao | AE95: Nao | AF95: 45518 | AG95: 46020 | AH95: 414.36 | AI95: 581.1 | AJ95: 4972.32 | AK95: 0 | AL95: 0 | AM95: 0 | AQ95: N | AS95: Juridica | AT95: Ativo | AU95: 101 | AV95: 10 | AW95: 1 | AX95: 45842 | AY95: SEX/ | AZ95: 46024 | BA95: 0 | BB95: 0 | BC95: 0 | BD95: 700 | BE95: 70 | BF95: 9 | BG95: 45536 | BH95: DOM/ | BI95: 46026 | BJ95: 0 | BK95: 0 | BL95: 0 | BM95: 0 | BN95: 0 | BO95: 0 | BP95: 2124.49 | BQ95: 2124.49 | BR95: 0 | BS95: 0 | BT95: 0 | BU95: 0 | BV95: 1789.73 | BW95: 1789.73 | BX95: 0 | BY95: 0 | BZ95: 0 | CA95: 0 | CB95: 1267.07 | CC95: AS 1-4
A96: 345 | B96: 2 | C96: 235 | D96: 804.950.953-20 | F96: VALTIM PITOMBEIRAS | G96: MARIA BERNADETE DE VASCONCELOS | H96: VIL DT PITOMBEIRAS 10000 | J96: PITOMBEIRAS | K96: CRUZ | L96: CE | M96: 62.595-000 | N96: 08 89700-6516 | O96: DEPOSITO DE BEBIDAS | P96: 0 | R96: 2 | S96: 92 | V96: 4163 | W96: 0 | X96: 4163 | Y96: 0 | Z96: 0 | AA96: 0 | AB96: 0 | AC96: 0 | AD96: Nao | AE96: Nao | AF96: 45518 | AG96: 46020 | AH96: 2692.2 | AI96: 10596.68 | AJ96: 37690.85 | AK96: 0 | AL96: 1507.3 | AM96: 0 | AQ96: N | AS96: Fisica | AT96: Ativo | AU96: 100 | AV96: 10 | AW96: 1 | AX96: 45842 | AY96: SEX/ | AZ96: 46024 | BA96: 0 | BB96: 0 | BC96: 0 | BD96: 700 | BE96: 70 | BF96: 9 | BG96: 45536 | BH96: DOM/ | BI96: 46026 | BJ96: 0 | BK96: 0 | BL96: 0 | BM96: 0 | BN96: 0 | BO96: 0 | BP96: 13959.13 | BQ96: 16654.11 | BR96: 0 | BS96: 0 | BT96: 0 | BU96: 0 | BV96: 8503.08 | BW96: 8828.08 | BX96: 0 | BY96: 0 | BZ96: 0 | CA96: 0 | CB96: 10580.61 | CC96: SUB
A97: 345 | B97: 2 | C97: 236 | D97: 010.945.843-55 | F97: MERCANTIL MF | G97: ROSA MARIA DE S. FREITAS | H97: R AV. TENENTE ALBANO 1450 | J97: CENTRO | K97: CRUZ | L97: CE | M97: 62.595-000 | N97: 88 89606-9537 | O97: ARMAZEM/MERCEARIA | P97: 0 | R97: 2 | S97: 90 | V97: 5000 | W97: 0 | X97: 5000 | Y97: 0 | Z97: 0 | AA97: 0 | AB97: 0 | AC97: 0 | AD97: Nao | AE97: Nao | AF97: 45518 | AG97: 46019 | AH97: 3714.57 | AI97: 5810.5 | AJ97: 48289.41 | AK97: 0 | AL97: 0 | AM97: 0 | AQ97: N | AS97: Fisica | AT97: Ativo | AU97: 105 | AV97: 10 | AW97: 1 | AX97: 45842 | AY97: SEX/ | AZ97: 46024 | BA97: 0 | BB97: 0 | BC97: 0 | BD97: 700 | BE97: 70 | BF97: 9 | BG97: 45536 | BH97: DOM/ | BI97: 46026 | BJ97: 0 | BK97: 0 | BL97: 0 | BM97: 0 | BN97: 0 | BO97: 0 | BP97: 17552.66 | BQ97: 17552.66 | BR97: 0 | BS97: 0 | BT97: 0 | BU97: 0 | BV97: 15373.13 | BW97: 15373.13 | BX97: 0 | BY97: 0 | BZ97: 0 | CA97: 0 | CB97: 16748.57 | CC97: TRAD
A98: 345 | B98: 2 | C98: 237 | D98: 064.843.253-08 | F98: MERC SALES LAGOA GR | G98: FRANCISCO DAS CHAGAS PEREIRA JUNIOR | H98: VIL DT LAGOA GRANDE 10000 | I98: Pista na esquina depois do WES | J98: LAGOA GRANDE | K98: ACARAU | L98: CE | M98: 62.580-000 | N98: 08 89977-4778 | O98: ARMAZEM/MERCEARIA | P98: 0 | R98: 6 | S98: 40 | V98: 0 | W98: 0 | X98: 0 | Y98: 0 | Z98: 0 | AA98: 0 | AB98: 0 | AC98: 0 | AD98: Nao | AE98: Nao | AF98: 45518 | AG98: 46019 | AH98: 506.81 | AI98: 1564.62 | AJ98: 6081.78 | AK98: 0 | AL98: 0 | AM98: 0 | AQ98: N | AS98: Fisica | AT98: Ativo | AU98: 102 | AV98: 10 | AW98: 1 | AX98: 45849 | AY98: SEX/ | AZ98: 46024 | BA98: 0 | BB98: 0 | BC98: 0 | BD98: 700 | BE98: 70 | BF98: 9 | BG98: 45536 | BH98: DOM/ | BI98: 46026 | BJ98: 0 | BK98: 0 | BL98: 0 | BM98: 0 | BN98: 0 | BO98: 0 | BP98: 2459.42 | BQ98: 2459.42 | BR98: 0 | BS98: 0 | BT98: 0 | BU98: 0 | BV98: 3008.49 | BW98: 3008.49 | BX98: 0 | BY98: 0 | BZ98: 0 | CA98: 0 | CB98: 1724.72 | CC98: TRAD
A99: 345 | B99: 2 | C99: 238 | D99: 834.727.623-49 | F99: MERCADINHO CHICHICO | G99: FRANCISCO PEDRO DE SOUZA NETO | H99: RUA Vila Moura 12 | I99: Pista | J99: VILA MOURA | K99: ACARAU | L99: CE | M99: 62.580-000 | N99: 88 99711-6924 | O99: ARMAZEM/MERCEARIA | P99: 0 | R99: 6 | S99: 41 | V99: 0 | W99: 0 | X99: 0 | Y99: 0 | Z99: 0 | AA99: 0 | AB99: 0 | AC99: 0 | AD99: Nao | AE99: Nao | AF99: 45518 | AG99: 46020 | AH99: 1198.71 | AI99: 2039.87 | AJ99: 9589.68 | AK99: 0 | AL99: 0 | AM99: 0 | AQ99: N | AS99: Fisica | AT99: Ativo | AU99: 101 | AV99: 10 | AW99: 1 | AX99: 45842 | AY99: SEX/ | AZ99: 46024 | BA99: 0 | BB99: 0 | BC99: 0 | BD99: 700 | BE99: 70 | BF99: 9 | BG99: 45536 | BH99: DOM/ | BI99: 46026 | BJ99: 0 | BK99: 0 | BL99: 0 | BM99: 0 | BN99: 0 | BO99: 0 | BP99: 4869.4 | BQ99: 4869.4 | BR99: 0 | BS99: 0 | BT99: 0 | BU99: 0 | BV99: 2758.82 | BW99: 2758.82 | BX99: 0 | BY99: 0 | BZ99: 0 | CA99: 0 | CB99: 3705.71 | CC99: AS 1-4
A100: 345 | B100: 2 | C100: 239 | D100: 13.595.724/0001-77 | F100: BAR O VALDECI MORAD | G100: JOSE VALDECI DO NASCIMENTO | H100: R PADRE LUIZ MARTINS SN | J100: MORADA NOVA | K100: ACARAU | L100: CE | M100: 62.580-000 | N100: 08 89937-5803 | O100: BAR/BARZINHO | P100: 0 | R100: 6 | S100: 40 | V100: 0 | W100: 0 | X100: 0 | Y100: 0 | Z100: 0 | AA100: 0 | AB100: 0 | AC100: 0 | AD100: Nao | AE100: Nao | AF100: 45518 | AG100: 46009 | AH100: 526.22 | AI100: 1013.83 | AJ100: 4736 | AK100: 0 | AL100: 0 | AM100: 0 | AQ100: N | AS100: Juridica | AT100: Ativo | AU100: 101 | AV100: 10 | AW100: 1 | AX100: 45812 | AY100: QUA/ | AZ100: 46022 | BA100: 0 | BB100: 0 | BC100: 0 | BD100: 700 | BE100: 70 | BF100: 9 | BG100: 45536 | BH100: DOM/ | BI100: 46026 | BJ100: 0 | BK100: 0 | BL100: 0 | BM100: 0 | BN100: 0 | BO100: 0 | BP100: 1889.33 | BQ100: 1889.33 | BR100: 0 | BS100: 0 | BT100: 0 | BU100: 0 | BV100: 1079.67 | BW100: 1079.67 | BX100: 0 | BY100: 0 | BZ100: 0 | CA100: 0 | CB100: 1699.18 | CC100: Rota
A101: 345 | B101: 2 | C101: 242 | D101: 684.248.683-15 | F101: COMERCIO PAULO DA CA | G101: FRANCISCO PAULO ORLANDO DE ARAUJO | H101: VL VILA MOURA SN | I101: NA CAIXA D AGUA A ESQUERDA | J101: VILA MOURA | K101: ACARAU | L101: CE | M101: 62.580-000 | N101: 88 99941-9904 | O101: ARMAZEM/MERCEARIA | P101: 0 | R101: 6 | S101: 41 | V101: 0 | W101: 0 | X101: 0 | Y101: 0 | Z101: 0 | AA101: 0 | AB101: 0 | AC101: 0 | AD101: Nao | AE101: Nao | AF101: 45518 | AG101: 46020 | AH101: 1393.96 | AI101: 3452.4 | AJ101: 15333.57 | AK101: 0 | AL101: 0 | AM101: 0 | AQ101: N | AS101: Fisica | AT101: Ativo | AU101: 101 | AV101: 10 | AW101: 1 | AX101: 45534 | AY101: SEX/ | AZ101: 46024 | BA101: 0 | BB101: 0 | BC101: 0 | BD101: 700 | BE101: 70 | BF101: 9 | BG101: 45536 | BH101: DOM/ | BI101: 46026 | BJ101: 0 | BK101: 0 | BL101: 0 | BM101: 0 | BN101: 0 | BO101: 0 | BP101: 7357.67 | BQ101: 7357.67 | BR101: 0 | BS101: 0 | BT101: 0 | BU101: 0 | BV101: 4502.49 | BW101: 4502.49 | BX101: 0 | BY101: 0 | BZ101: 0 | CA101: 0 | CB101: 3862.54 | CC101: TRAD
A102: 345 | B102: 2 | C102: 243 | D102: 868.436.213-68 | F102: MERC ROBERIO CORREG | G102: ANTONIO ARAUJO DOS SANTOS | H102: RUA CE 085 - CORREGUINHO DO MUNIZ 2451 | J102: CORREGUINHO DO MUNIZ | K102: CRUZ | L102: CE | M102: 62.595-000 | N102: 88 99796-2232 | O102: ARMAZEM/MERCEARIA | P102: 0 | R102: 6 | S102: 40 | V102: 0 | W102: 0 | X102: 0 | Y102: 0 | Z102: 0 | AA102: 0 | AB102: 0 | AC102: 0 | AD102: Nao | AE102: Nao | AF102: 45518 | AG102: 46020 | AH102: 1168.03 | AI102: 2742 | AJ102: 11680.33 | AK102: 0 | AL102: 0 | AM102: 0 | AQ102: N | AS102: Fisica | AT102: Ativo | AU102: 100 | AV102: 10 | AW102: 1 | AX102: 45842 | AY102: SEX/ | AZ102: 46024 | BA102: 0 | BB102: 0 | BC102: 0 | BD102: 700 | BE102: 70 | BF102: 9 | BG102: 45536 | BH102: DOM/ | BI102: 46026 | BJ102: 0 | BK102: 0 | BL102: 0 | BM102: 0 | BN102: 0 | BO102: 0 | BP102: 6705.64 | BQ102: 6705.64 | BR102: 0 | BS102: 0 | BT102: 0 | BU102: 0 | BV102: 4111.19 | BW102: 4111.19 | BX102: 0 | BY102: 0 | BZ102: 0 | CA102: 0 | CB102: 2771.34 | CC102: TRAD
A103: 345 | B103: 2 | C103: 245 | D103: 026.864.263-06 | F103: COMERCIO FREITAS AC | G103: MARIA ELIONE FERREIRA ARAUJO | H103: RUA CORONEL SALES 1072 | J103: ACUDE NOVO | K103: ACARAU | L103: CE | M103: 62.580-000 | N103: 08 89805-2379 | O103: ARMAZEM/MERCEARIA | P103: 0 | R103: 6 | S103: 39 | V103: 0 | W103: 0 | X103: 0 | Y103: 0 | Z103: 0 | AA103: 0 | AB103: 0 | AC103: 0 | AD103: Nao | AE103: Nao | AF103: 45518 | AG103: 46020 | AH103: 578.37 | AI103: 1034.7 | AJ103: 2891.86 | AK103: 0 | AL103: 0 | AM103: 0 | AQ103: N | AS103: Fisica | AT103: Ativo | AU103: 101 | AV103: 10 | AW103: 1 | AX103: 45535 | AY103: SAB/ | AZ103: 46025 | BA103: 0 | BB103: 0 | BC103: 0 | BD103: 700 | BE103: 70 | BF103: 9 | BG103: 45536 | BH103: DOM/ | BI103: 46026 | BJ103: 0 | BK103: 0 | BL103: 0 | BM103: 0 | BN103: 0 | BO103: 0 | BP103: 1125.52 | BQ103: 1125.52 | BR103: 0 | BS103: 0 | BT103: 0 | BU103: 0 | BV103: 731.64 | BW103: 731.64 | BX103: 0 | BY103: 0 | BZ103: 0 | CA103: 0 | CB103: 839.18 | CC103: TRAD
A104: 345 | B104: 2 | C104: 246 | D104: 04.520.082/0001-56 | F104: MERCADINHO MENOR PRE | G104: JOSE M ARAUJO MERCADINHO | H104: RUA SAO PAULO 10000 | J104: PEDRINHAS | K104: ACARAU | L104: CE | M104: 62.580-000 | N104: 88 99607-2496 | O104: ARMAZEM/MERCEARIA | P104: 0 | R104: 6 | S104: 44 | V104: 0 | W104: 0 | X104: 0 | Y104: 0 | Z104: 0 | AA104: 0 | AB104: 0 | AC104: 0 | AD104: Nao | AE104: Nao | AF104: 45518 | AG104: 46010 | AH104: 372.17 | AI104: 514.44 | AJ104: 2605.2 | AK104: 0 | AL104: 0 | AM104: 0 | AQ104: N | AS104: Juridica | AT104: Ativo | AU104: 101 | AV104: 10 | AW104: 1 | AX104: 45967 | AY104: QUI/ | AZ104: 46023 | BA104: 0 | BB104: 0 | BC104: 0 | BD104: 700 | BE104: 70 | BF104: 9 | BG104: 45536 | BH104: DOM/ | BI104: 46026 | BJ104: 0 | BK104: 0 | BL104: 0 | BM104: 0 | BN104: 0 | BO104: 0 | BP104: 834.84 | BQ104: 834.84 | BR104: 0 | BS104: 0 | BT104: 0 | BU104: 0 | BV104: 964.06 | BW104: 964.06 | BX104: 0 | BY104: 0 | BZ104: 0 | CA104: 0 | CB104: 752.72 | CC104: TRAD
A105: 345 | B105: 2 | C105: 247 | D105: 067.102.413-27 | F105: BAR PAIXAO VELHA TI | G105: JOSE RAIMUNDO SILVEIRA | H105: RUA SITIO TIMBIRA 10000 | J105: TIMBIRA | K105: BELA CRUZ | L105: CE | M105: 62.570-000 | N105: 08 89936-0890 | O105: BAR/BARZINHO | P105: 0 | R105: 6 | S105: 36 | V105: 0 | W105: 0 | X105: 0 | Y105: 0 | Z105: 0 | AA105: 0 | AB105: 0 | AC105: 0 | AD105: Nao | AE105: Nao | AF105: 45518 | AG105: 46014 | AH105: 356.28 | AI105: 634.66 | AJ105: 2493.96 | AK105: 0 | AL105: 0 | AM105: 0 | AQ105: N | AS105: Fisica | AT105: Ativo | AU105: 105 | AV105: 10 | AW105: 1 | AX105: 45831 | AY105: SEG/ | AZ105: 46027 | BA105: 0 | BB105: 0 | BC105: 0 | BD105: 700 | BE105: 70 | BF105: 9 | BG105: 45536 | BH105: DOM/ | BI105: 46026 | BJ105: 0 | BK105: 0 | BL105: 0 | BM105: 0 | BN105: 0 | BO105: 0 | BP105: 251.6 | BQ105: 251.6 | BR105: 0 | BS105: 0 | BT105: 0 | BU105: 0 | BV105: 957.88 | BW105: 957.88 | BX105: 0 | BY105: 0 | BZ105: 0 | CA105: 0 | CB105: 773.45 | CC105: Rota
...
